Workbook

Sheet ①指标库
A1: 奶牛养殖核心指标库（指标字典 · 数据来源已逐项核对档案表）
A2: 说明：① 可得性评级——A=档案表现有字段可直接汇总；B=需跨表关联/DHI测定匹配/阈值判定；C=现有档案无字段，需费用台账补采或对接财务。② 参考值为规模化奶牛场（万头级/标准化千头级）行业通行基准，用于看板阈值线与达标判定。③ 表号对应《畜禽养殖档案管理表格（全套）》。④ N列评级代码为统计与筛选字段，供报告页公式和看板自动汇总。
A3: 指标大类 | B3: 指标名称 | C3: 单位 | D3: 计算公式 | E3: 参考下限 | F3: 参考上限 | G3: 优秀/目标值 | H3: 数据来源表号 | I3: 关键字段（已核对档案表） | J3: 指标优先级 | K3: 数据可得性 | L3: 可视化适配 | M3: 验证说明与行业标准 | N3: 评级代码
A4: 产奶性能 | B4: 成母牛年均单产(305天) | C4: kg/头 | D4: 统计期产奶总重÷平均成母牛存栏头数 | E4: 9500 | F4: 12000 | G4: 11500 | H4: 02-18、01-07 | I4: 02-18 J总产奶量；01-07成母牛存栏 | J4: 核心 | K4: A 直接可得 | L4: KPI卡片、年度趋势柱状图 | M4: 规模化荷斯坦牛单产标杆，万头牧场平均超10.5吨 | N4: A
A5: 产奶性能 | B5: 泌乳牛日均单产 | C5: kg/头/天 | D5: 当月总产奶量÷当月泌乳牛日均头数÷当月天数 | E5: 30 | F5: 38 | G5: 35 | H5: 02-18、01-07 | I5: 02-18 J日产奶量；01-07泌乳牛头数 | J5: 核心 | K5: B 加工可得 | L5: 月度折线图、分舍对比 | M5: 反映牧场日常精细化饲养管理水平，随泌乳天数变动 | N5: B
A6: 产奶性能 | B6: 高峰日产奶量 | C6: kg/头/天 | D6: 牛群分娩后40-60天日最高单产平均值 | E6: 38 | F6: 48 | G6: 45 | H6: 02-18 DHI测定 | I6: 02-18 DHI产奶峰值记录 | J6: 常规 | K6: B 加工可得 | L6: 泌乳曲线、胎次分布图 | M6: 产奶潜能核心观测值，直接决定全期产奶总量 | N6: B
A7: 产奶性能 | B7: 生鲜牛乳脂率 | C7: % | D7: 生鲜乳脂肪含量总重量÷鲜乳总重量 | E7: 0.037 | F7: 0.042 | G7: 0.0395 | H7: 02-18、06-02 | I7: 02-18 K乳脂率；06-02化验单 | J7: 核心 | K7: A 直接可得 | L7: 月度折线图、品质双轴图 | M7: 中国优质牧场标准≥3.90%，欧盟标准3.80% | N7: A
A8: 产奶性能 | B8: 生鲜牛乳蛋白率 | C8: % | D8: 生鲜乳蛋白质含量总重量÷鲜乳总重量 | E8: 0.031 | F8: 0.035 | G8: 0.0335 | H8: 02-18、06-02 | I8: 02-18 L乳蛋白率；06-02化验单 | J8: 核心 | K8: A 直接可得 | L8: 月度折线图、品质双轴图 | M8: 中国规模化牧场平均≥3.34%，直接关联收购定价 | N8: A
A9: 产奶性能 | B9: 体细胞数 SCC | C9: 万/mL | D9: 生鲜乳体细胞实验室仪器测定均值 | F9: 20 | G9: 15 | H9: 02-18、04-03 | I9: 02-18 M体细胞数；04-03检测 | J9: 核心 | K9: A 直接可得 | L9: 月度折线图、阈值预警线 | M9: 隐性乳房炎核心预警红线，>20万触发分群与检疗 | N9: A
A10: 产奶性能 | B10: 菌落总数 | C10: 万CFU/mL | D10: 原奶微生物细菌菌落总数测定值 | F10: 10 | G10: 5 | H10: 02-18、06-02 | I10: 02-18 N菌落总数；06-02验收单 | J10: 常规 | K10: A 直接可得 | L10: 合规达标卡片 | M10: 生鲜乳卫生安全指标，特品原奶要求≤5万CFU/mL | N10: A
A11: 产奶性能 | B11: 泌乳牛比例 | C11: % | D11: 当期在挤泌乳牛头数÷成母牛存栏总头数 | E11: 0.82 | F11: 0.88 | G11: 0.85 | H11: 01-07 | I11: 01-07存栏月报泌乳牛/成母牛 | J11: 常规 | K11: B 加工可得 | L11: 仪表盘、结构饼图 | M11: 过低说明干奶牛或不孕牛占比过高，严重侵蚀效益 | N11: B
A12: 繁殖育种 | B12: 产犊间隔 | C12: 天 | D12: 全年经产母牛相邻两胎产犊间隔总天数÷头数 | E12: 390 | F12: 420 | G12: 400 | H12: 02-09、02-06 | I12: 02-09 B分娩日期；02-06繁殖记录卡 | J12: 核心 | K12: B 加工可得 | L12: 分布直方图、年度趋势 | M12: 繁殖效率核心指标，超420天显著增加无效饲养天数 | N12: B
A13: 繁殖育种 | B13: 21天怀孕率 (PR) | C13: % | D13: 21天妊娠牛数÷21天内适合配种牛数 | E13: 0.18 | F13: 0.25 | G13: 0.22 | H13: 02-07、02-09 | I13: 02-07配种/妊检；02-09分娩 | J13: 核心 | K13: B 加工可得 | L13: 月度趋势图、配种雷达图 | M13: 繁殖管理黄金指标，PR = 发情揭发率 × 情期受胎率 | N13: B
A14: 繁殖育种 | B14: 配种发情揭发率 (HD) | C14: % | D14: 21天内实际发情配种牛数÷应配种牛数 | E14: 0.55 | F14: 0.7 | G14: 0.65 | H14: 02-07 | I14: 02-07 G配种日期、发情记录 | J14: 常规 | K14: B 加工可得 | L14: 柱状图、班组对比 | M14: 配合项圈与计步器智能监控发情表现 | N14: B
A15: 繁殖育种 | B15: 情期受胎率 (CR) | C15: % | D15: 妊娠诊断阳性牛数÷总配种情期数 | E15: 0.35 | F15: 0.45 | G15: 0.4 | H15: 02-07 | I15: 02-07 L妊检结果(阳性)/配种记录 | J15: 常规 | K15: B 加工可得 | L15: 月度折线图、公牛对比 | M15: 衡量精液品质、人工授精操作与母牛受孕机能 | N15: B
A16: 繁殖育种 | B16: 空怀天数 (DO) | C16: 天 | D16: 母牛产犊至再次受孕成功的间隔天数 | E16: 105 | F16: 140 | G16: 120 | H16: 02-07、02-09 | I16: 02-07受孕日期 - 02-09分娩日期 | J16: 常规 | K16: B 加工可得 | L16: 胎次箱线图 | M16: 每增加1天空怀天数，头均增加饲养成本约30-40元 | N16: B
A17: 繁殖育种 | B17: 犊牛初生重 | C17: kg/头 | D17: 犊牛出生后称重均值 | E17: 36 | F17: 44 | G17: 40 | H17: 02-09 | I17: 02-09 M初生重字段已内置 | J17: 常规 | K17: A 直接可得 | L17: 分布直方图 | M17: 母系营养与后备牛培育起步指标，公母分别建档 | N17: A
A18: 健康死淘 | B18: 犊牛成活率(0-60日龄) | C18: % | D18: 断奶存活犊牛数÷出生活仔犊牛数 | E18: 0.95 | F18: 0.98 | G18: 0.96 | H18: 02-10、02-09 | I18: 02-10成活率/断奶数；02-09活仔数 | J18: 核心 | K18: A 直接可得 | L18: 月度折线、原因分析饼图 | M18: 未来高产牛群底座，初乳灌服与岛式犊牛舍管护 | N18: A
A19: 健康死淘 | B19: 育成牛成活率 | C19: % | D19: 配种受孕育成牛数÷进入育成期青年牛数 | E19: 0.96 | F19: 0.99 | G19: 0.98 | H19: 01-07、02-07 | I19: 01-07育成存栏变动；02-07初配 | J19: 常规 | K19: B 加工可得 | L19: 阶段漏斗图 | M19: 成活率高保证牧场自主更新良性扩群 | N19: B
A20: 健康死淘 | B20: 成母牛年淘汰率 | C20: % | D20: 全年淘汰成母牛数÷平均成母牛存栏头数 | E20: 0.25 | F20: 0.32 | G20: 0.28 | H20: 01-07、02-16 | I20: 01-07 K淘汰数；02-16淘汰原因 | J20: 常规 | K20: B 加工可得 | L20: 饼图、淘汰病因树状图 | M20: 正常自繁更替28%左右，过高代表肢蹄或乳腺疾病多发 | N20: B
A21: 健康死淘 | B21: 成母牛月死亡率 | C21: % | D21: 当月病死成母牛数÷月均成母牛存栏 | F21: 0.008 | G21: 0.005 | H21: 01-07、05-01 | I21: 01-07 J死亡；05-01病死无害化 | J21: 核心 | K21: A 直接可得 | L21: 月度折线、红线预警图 | M21: 阈值0.8%，主要防范产后瘫痪、真胃移位与严重创伤 | N21: A
A22: 健康死淘 | B22: 临床乳房炎月发病率 | C22: % | D22: 当月发生临床乳房炎牛次÷泌乳牛平均头数 | F22: 0.03 | G22: 0.02 | H22: 04-09、02-18 | I22: 04-09诊疗记录；02-18在挤牛数 | J22: 核心 | K22: B 加工可得 | L22: 月度走势、病原菌分布 | M22: 乳腺炎直接导致弃奶损失与医药费用增加 | N22: B
A23: 饲养管理 | B23: 料奶比 (FMR) | C23: :1 | D23: 统计期总饲料干物质消耗量(kg)÷产奶量(kg) | E23: 1.35 | F23: 1.65 | G23: 1.45 | H23: 02-01/03-07、02-18 | I23: 02-01 TMR投喂；02-18产奶总量 | J23: 核心 | K23: B 加工可得 | L23: 月度折线图、效益散点图 | M23: 衡量TMR日粮配合技术与饲料转化效率 | N23: B
A24: 饲养管理 | B24: 泌乳牛干物质采食量 | C24: kg/天 | D24: 每头泌乳牛日均摄入日粮干物质千克数 | E24: 22 | F24: 26 | G24: 24 | H24: 02-01 TMR记录 | I24: 02-01实际采食量×干物质率 | J24: 常规 | K24: B 加工可得 | L24: 季节采食曲线、热应激分析 | M24: 夏季热应激易导致采食量骤降与酸中毒 | N24: B
A25: 饲养管理 | B25: 生鲜乳休药期合规率 | C25: % | D25: 无抗原奶批次÷交付原奶总批次 | G25: 1 | H25: 03-08、06-02 | I25: 03-08休药期截止；06-02交售记录 | J25: 核心 | K25: B 加工可得 | L25: 合规仪表盘、红线拦截 | M25: 用药牛进入病牛舍弃奶，休药期满方可回归正常挤奶 | N25: B
A26: 饲养管理 | B26: 病死牛无害化处理率 | C26: % | D26: 规范无害化处理病死牛数÷病死牛总数 | G26: 1 | H26: 05-01、01-07 | I26: 05-01数量；01-07死亡记录 | J26: 核心 | K26: B 加工可得 | L26: 合规达标卡片 | M26: 农业部法定六大台账底线，与存栏死亡严格勾稽 | N26: B
A27: 饲养管理 | B27: 奶牛耳标佩戴率 | C27: % | D27: 实际佩戴国家统一耳标数÷应加施标识数 | G27: 1 | H27: 01-06、01-07 | I27: 01-06标识记录；01-07存栏 | J27: 常规 | K27: B 加工可得 | L27: 达标进度条 | M27: 双耳标或RFID电子耳标佩戴率100% | N27: B
A28: 成本效益 | B28: 公斤奶完全成本 | C28: 元/kg | D28: (饲料+兽药+人工+折旧+能耗+防疫)÷产奶量 | E28: 3.2 | F28: 3.8 | G28: 3.4 | H28: 03-01、10-01、02-18 | I28: 03-01饲料；10-01费用台账；02-18产奶量 | J28: 核心 | K28: C 缺口需补采 | L28: 成本结构瀑布图、盈亏平衡线 | M28: 依赖《10-01月度费用台账》补采人工、折旧、水电 | N28: C
A29: 成本效益 | B29: 公斤奶饲料成本 | C29: 元/kg | D29: 生鲜乳生产饲料消耗总金额÷产奶总量 | E29: 2.1 | F29: 2.5 | G29: 2.25 | H29: 03-01、03-07、02-18 | I29: 03-01采购单价；03-07消耗；02-18奶量 | J29: 核心 | K29: B 加工可得 | L29: 月度走势图、占比分析 | M29: 饲料占公斤奶总成本约60%-65% | N29: B
A30: 成本效益 | B30: 原料奶销售均价 | C30: 元/kg | D30: 当期生鲜乳销售总金额÷生鲜乳销售总重量 | E30: 3.7 | F30: 4.4 | G30: 4.1 | H30: 06-02 | I30: 06-02 X销售单价、Y销售金额 | J30: 核心 | K30: A 直接可得 | L30: 价格波动曲线、指标溢价分析 | M30: 根据优质乳蛋白、乳脂率及体细胞数享受优质优价阶梯加价 | N30: A
A31: 成本效益 | B31: 成母牛年头均净利润 | C31: 元/头 | D31: (销售收入-总成本)÷成母牛平均存栏数 | E31: 2500 | F31: 6000 | G31: 4500 | H31: 06-02、10-01、01-07 | I31: 收入减总成本后除以存栏 | J31: 核心 | K31: C 缺口需补采 | L31: 利润走势折线、盈亏仪表盘 | M31: 规模牧场最终经营成果量化指标 | N31: C

Sheet ②可行性验证报告
A1: 奶牛指标体系可行性验证报告（档案数据 → 奶牛指标 → 看板 全链路核查）
A3: 一、验证方法：以《畜禽养殖档案管理表格（全套）》结合奶牛专项（DHI测定、生鲜乳销售、产奶台账）为基准，核查单产、乳品质、繁殖率、饲喂转化率与成本效益公式闭环；并在「③演算-数据录入」「④演算-指标计算」中以一个1000头成母牛现代化牧场的12个月连续模拟数据完成全量公式演练（预置高温热应激月份与体细胞异常，校验自动预警敏感度）。
A5: 二、验证结论总览（公式实时统计自①指标库）
A6: 可得性评级 | B6: 指标数量 | C6: 占比 | D6: 含义
A7: A 直接可得 | B7: =COUNTIF('①指标库'!N4:N31,"A") | C7: =B7/B10 | D7: 档案表现有字段（02-18产奶、06-02产品销售、02-09分娩等）直接汇总
A8: B 加工可得 | B8: =COUNTIF('①指标库'!N4:N31,"B") | C8: =B8/B10 | D8: 字段齐备，需跨表关联/DHI测定批次匹配/日均换算/阈值规则
A9: C 缺口需补采 | B9: =COUNTIF('①指标库'!N4:N31,"C") | C9: =B9/B10 | D9: 涉及全成本与头均利润，依赖《10-01月度费用台账》补采人工折旧能耗
A10: 合计 | B10: =SUM(B7:B9) | C10: =SUM(C7:C9) | D10: 现有档案可支撑率 = A+B 占比
A11: 现有档案可支撑率（A+B） | B11: =B7+B8 | C11: =B11/B10 | D11: 28项指标中26项可直接或加工得出（占比92.9%）
A13: 三、奶牛关键缺口与档案升级方案（产品化改版点）
A14: 序号 | B14: 业务缺口 | C14: 影响奶牛核心指标 | D14: 档案升级方案 | E14: 落地动作
A15: 1 | B15: 原档案缺少连续日产奶与DHI化验台账 | C15: 年单产、乳脂率、乳蛋白率、体细胞数SCC | D15: 新增《02-18 奶牛产奶与DHI检测记录表》，集成日产奶量与乳成分检验记录 | E15: 新建专项表单
A16: 2 | B16: 原档案未细分干奶牛、围产牛与成母牛淘汰 | C16: 泌乳牛比例、淘汰率、产犊间隔 | D16: 在01-07存栏表畜禽类别枚举增加‘泌乳牛、干奶牛、育成牛、哺乳犊牛’ | E16: 扩展下拉枚举
A17: 3 | B17: 生鲜乳销售单价与质量阶梯未明确 | C17: 公斤奶售价、生鲜乳销售收入 | D17: 06-02产品销售表明确‘生鲜乳(原料奶)’品名，增设优质优价加价列 | E17: 对齐销售口径
A18: 4 | B18: 缺少TMR日粮干物质投喂记录 | C18: 料奶比(FMR)、干物质采食量(DMI) | D18: 在02-01饲料使用记录表增加‘日粮干物质率(%)与投喂量’ | E18: 字段规范微调
A19: 5 | B19: 奶牛全生命周期跨期长达数年 | C19: 产犊间隔、全群胎次结构 | D19: 利用02-06种畜卡和耳标唯一标识打通胎次关联 | E19: 规则勾稽
A21: 四、公式闭环验证结论（自动比对判定）
A22: 验证项 | B22: 期望结果 | C22: 实际结果（公式） | D22: 判定
A23: 存栏勾稽：12个月成母牛期末=期初+初产青年牛-淘汰-死亡 | B23: 12个月全部平衡 | C23: =COUNTIF('③演算-数据录入'!AL6:AL17,"不平衡")&"个不平衡月" | D23: =IF(VALUE(LEFT(C23,FIND("个",C23)-1))=0,"通过","检出异常(符合预期)")
A24: 无害化勾稽：病死无害化处理数=病死牛数 | B24: 12个月全部一致 | C24: =COUNTIF('③演算-数据录入'!AM6:AM17,"不一致")&"个不一致月" | D24: =IF(VALUE(LEFT(C24,FIND("个",C24)-1))=0,"通过","检出异常(符合预期)")
A25: 体细胞数(SCC)超标预警（预置7月热应激异常，SCC达24万） | B25: 检出1个超标月 | C25: =COUNTIF('④演算-指标计算'!H6:H17,">20")&"个超标月" | D25: =IF(VALUE(LEFT(C25,FIND("个",C25)-1))=0,"通过","检出异常(符合预期)")
A26: 成母牛死亡率预警逻辑（预置冬季1月异常，月死亡率0.9%） | B26: 检出1个超标月 | C26: =COUNTIF('④演算-指标计算'!M6:M17,">0.008")&"个超标月" | D26: =IF(VALUE(LEFT(C26,FIND("个",C26)-1))=0,"通过","检出异常(符合预期)")
A27: 核心指标年度阈值断言（单产>11吨/料奶比<1.5/休药期合规等） | B27: 全部达标或优秀 | C27: =COUNTIF('④演算-指标计算'!H22:H39,"异常")&"个异常项" | D27: =IF(VALUE(LEFT(C27,FIND("个",C27)-1))=0,"通过","检出异常(符合预期)")

Sheet ③演算-数据录入
A1: ③ 演算-数据录入区（模拟1000头成母牛现代化奶牛牧场 · 2026年1-12月 · 数据用于验证公式）
A2: 录入说明：白底列为牧场日常台账采集数据；成母牛存栏按 01-07 勾稽关系严格闭环。预置异常：7月热应激导致体细胞数SCC超标至24万，1月寒潮导致成母牛死亡率偏高，用于验证阈值判定有效性。
A3: 月份 | B3: 期初成母牛 | C3: 期末成母牛 | D3: 期初全群存栏 | E3: 初产育成牛转入 | F3: 购入引进牛 | G3: 出栏与淘汰 | H3: 死亡 | I3: 泌乳牛头数 | J3: 干奶牛头数 | K3: 犊牛出生数 | L3: 犊牛成活数 | M3: 月产奶量(kg) | N3: 生鲜乳销量(kg) | O3: 乳脂率(%) | P3: 乳蛋白率(%) | Q3: 体细胞数(万/mL) | R3: 菌落数(万CFU/mL) | S3: 配种头次 | T3: 受孕头次 | U3: 干物质采食量DMI(kg) | V3: 总饲喂干物质(kg) | W3: 出乳批次 | X3: 休药期合规批次 | Y3: 病死牛数 | Z3: 无害化处理数 | AA3: 耳标佩戴数 | AB3: 环境记录天数 | AC3: 温湿度指数THI达标天数 | AD3: 临床乳房炎发生头次 | AE3: 粗饲料金额(元) | AF3: 精饲料金额(元) | AG3: 兽药防疫费(元) | AH3: 人工折旧能耗费用(元) | AI3: 原料奶售价(元/kg) | AJ3: 淘汰母牛收入(元) | AK3: 期末全群存栏 | AL3: 存栏平衡校验 | AM3: 无害化勾稽
A6: 1月 | B6: 998 | C6: 1000 | D6: 2100 | E6: 25 | F6: 0 | G6: 20 | H6: 9 | I6: 850 | J6: 150 | K6: 88 | L6: 84 | M6: 920000 | N6: 906200 | O6: 0.0405 | P6: 0.0342 | Q6: 16.5 | R6: 4.5 | S6: 110 | T6: 45 | U6: 24.5 | V6: 645575 | W6: 62 | X6: 62 | Y6: 9 | Z6: 9 | AA6: 1000 | AB6: 31 | AC6: 30 | AD6: 18 | AE6: 1000641 | AF6: 936084 | AG6: 85000 | AH6: 650000 | AI6: 4.15 | AJ6: 240000 | AK6: =D6+E6+K6-G6-H6 | AL6: =IF(AK6=D6+E6+K6-G6-H6,"平衡","不平衡") | AM6: =IF(Z6=Y6,"一致","不一致")
A7: 2月 | B7: =C6 | C7: 1005 | D7: =AK6 | E7: 28 | F7: 0 | G7: 22 | H7: 6 | I7: 855 | J7: 150 | K7: 82 | L7: 78 | M7: 860000 | N7: 847100 | O7: 0.0402 | P7: 0.034 | Q7: 15.8 | R7: 4.2 | S7: 105 | T7: 43 | U7: 24.8 | V7: 593712 | W7: 56 | X7: 56 | Y7: 6 | Z7: 6 | AA7: 1005 | AB7: 28 | AC7: 28 | AD7: 16 | AE7: 920254 | AF7: 860882 | AG7: 80000 | AH7: 650000 | AI7: 4.12 | AJ7: 264000 | AK7: =D7+E7+K7-G7-H7 | AL7: =IF(AK7=D7+E7+K7-G7-H7,"平衡","不平衡") | AM7: =IF(Z7=Y7,"一致","不一致")
A8: 3月 | B8: =C7 | C8: 1010 | D8: =AK7 | E8: 30 | F8: 0 | G8: 24 | H8: 7 | I8: 860 | J8: 150 | K8: 90 | L8: 86 | M8: 960000 | N8: 945600 | O8: 0.0398 | P8: 0.0338 | Q8: 16.2 | R8: 4.8 | S8: 112 | T8: 46 | U8: 25 | V8: 666500 | W8: 62 | X8: 62 | Y8: 7 | Z8: 7 | AA8: 1010 | AB8: 31 | AC8: 31 | AD8: 17 | AE8: 1033075 | AF8: 966425 | AG8: 88000 | AH8: 650000 | AI8: 4.1 | AJ8: 288000 | AK8: =D8+E8+K8-G8-H8 | AL8: =IF(AK8=D8+E8+K8-G8-H8,"平衡","不平衡") | AM8: =IF(Z8=Y8,"一致","不一致")
A9: 4月 | B9: =C8 | C9: 1015 | D9: =AK8 | E9: 28 | F9: 0 | G9: 22 | H9: 7 | I9: 865 | J9: 150 | K9: 86 | L9: 82 | M9: 940000 | N9: 925900 | O9: 0.0395 | P9: 0.0335 | Q9: 17 | R9: 4.6 | S9: 108 | T9: 44 | U9: 24.6 | V9: 638370 | W9: 60 | X9: 60 | Y9: 7 | Z9: 7 | AA9: 1015 | AB9: 30 | AC9: 30 | AD9: 19 | AE9: 989474 | AF9: 925636 | AG9: 86000 | AH9: 650000 | AI9: 4.08 | AJ9: 264000 | AK9: =D9+E9+K9-G9-H9 | AL9: =IF(AK9=D9+E9+K9-G9-H9,"平衡","不平衡") | AM9: =IF(Z9=Y9,"一致","不一致")
A10: 5月 | B10: =C9 | C10: 1012 | D10: =AK9 | E10: 25 | F10: 0 | G10: 26 | H10: 6 | I10: 860 | J10: 152 | K10: 84 | L10: 80 | M10: 930000 | N10: 916050 | O10: 0.0392 | P10: 0.0332 | Q10: 18.2 | R10: 5.2 | S10: 106 | T10: 43 | U10: 24 | V10: 639840 | W10: 62 | X10: 62 | Y10: 6 | Z10: 6 | AA10: 1012 | AB10: 31 | AC10: 29 | AD10: 22 | AE10: 991752 | AF10: 927768 | AG10: 92000 | AH10: 650000 | AI10: 4.05 | AJ10: 312000 | AK10: =D10+E10+K10-G10-H10 | AL10: =IF(AK10=D10+E10+K10-G10-H10,"平衡","不平衡") | AM10: =IF(Z10=Y10,"一致","不一致")
A11: 6月 | B11: =C10 | C11: 1008 | D11: =AK10 | E11: 24 | F11: 0 | G11: 27 | H11: 5 | I11: 855 | J11: 153 | K11: 88 | L11: 84 | M11: 910000 | N11: 896350 | O11: 0.0388 | P11: 0.033 | Q11: 19.5 | R11: 5.8 | S11: 110 | T11: 44 | U11: 23.2 | V11: 595080 | W11: 60 | X11: 60 | Y11: 5 | Z11: 5 | AA11: 1008 | AB11: 30 | AC11: 25 | AD11: 25 | AE11: 922374 | AF11: 862866 | AG11: 98000 | AH11: 650000 | AI11: 4.02 | AJ11: 324000 | AK11: =D11+E11+K11-G11-H11 | AL11: =IF(AK11=D11+E11+K11-G11-H11,"平衡","不平衡") | AM11: =IF(Z11=Y11,"一致","不一致")
A12: 7月 | B12: =C11 | C12: 1005 | D12: =AK11 | E12: 26 | F12: 0 | G12: 28 | H12: 5 | I12: 850 | J12: 155 | K12: 85 | L12: 81 | M12: 880000 | N12: 866800 | O12: 0.0382 | P12: 0.0325 | Q12: 24 | R12: 6.5 | S12: 108 | T12: 42 | U12: 22 | V12: 579700 | W12: 62 | X12: 62 | Y12: 5 | Z12: 5 | AA12: 1005 | AB12: 31 | AC12: 20 | AD12: 32 | AE12: 898535 | AF12: 840565 | AG12: 115000 | AH12: 650000 | AI12: 3.98 | AJ12: 336000 | AK12: =D12+E12+K12-G12-H12 | AL12: =IF(AK12=D12+E12+K12-G12-H12,"平衡","不平衡") | AM12: =IF(Z12=Y12,"一致","不一致")
A13: 8月 | B13: =C12 | C13: 1008 | D13: =AK12 | E13: 28 | F13: 0 | G13: 24 | H13: 6 | I13: 852 | J13: 156 | K13: 83 | L13: 79 | M13: 890000 | N13: 876650 | O13: 0.0385 | P13: 0.0328 | Q13: 19.8 | R13: 5.9 | S13: 105 | T13: 41 | U13: 22.5 | V13: 594270 | W13: 62 | X13: 62 | Y13: 6 | Z13: 6 | AA13: 1008 | AB13: 31 | AC13: 22 | AD13: 26 | AE13: 921118 | AF13: 861692 | AG13: 105000 | AH13: 650000 | AI13: 4.02 | AJ13: 288000 | AK13: =D13+E13+K13-G13-H13 | AL13: =IF(AK13=D13+E13+K13-G13-H13,"平衡","不平衡") | AM13: =IF(Z13=Y13,"一致","不一致")
A14: 9月 | B14: =C13 | C14: 1012 | D14: =AK13 | E14: 30 | F14: 0 | G14: 25 | H14: 5 | I14: 858 | J14: 154 | K14: 89 | L14: 85 | M14: 930000 | N14: 916050 | O14: 0.0392 | P14: 0.0332 | Q14: 17.5 | R14: 5 | S14: 112 | T14: 46 | U14: 23.8 | V14: 612612 | W14: 60 | X14: 60 | Y14: 5 | Z14: 5 | AA14: 1012 | AB14: 30 | AC14: 28 | AD14: 20 | AE14: 949549 | AF14: 888287 | AG14: 90000 | AH14: 650000 | AI14: 4.06 | AJ14: 300000 | AK14: =D14+E14+K14-G14-H14 | AL14: =IF(AK14=D14+E14+K14-G14-H14,"平衡","不平衡") | AM14: =IF(Z14=Y14,"一致","不一致")
A15: 10月 | B15: =C14 | C15: 1015 | D15: =AK14 | E15: 31 | F15: 0 | G15: 27 | H15: 5 | I15: 862 | J15: 153 | K15: 87 | L15: 83 | M15: 950000 | N15: 935750 | O15: 0.0398 | P15: 0.0336 | Q15: 16 | R15: 4.5 | S15: 110 | T15: 45 | U15: 24.6 | V15: 657361 | W15: 62 | X15: 62 | Y15: 5 | Z15: 5 | AA15: 1015 | AB15: 31 | AC15: 31 | AD15: 17 | AE15: 1018910 | AF15: 953173 | AG15: 85000 | AH15: 650000 | AI15: 4.1 | AJ15: 324000 | AK15: =D15+E15+K15-G15-H15 | AL15: =IF(AK15=D15+E15+K15-G15-H15,"平衡","不平衡") | AM15: =IF(Z15=Y15,"一致","不一致")
A16: 11月 | B16: =C15 | C16: 1018 | D16: =AK15 | E16: 29 | F16: 0 | G16: 25 | H16: 4 | I16: 865 | J16: 153 | K16: 85 | L16: 81 | M16: 940000 | N16: 925900 | O16: 0.0402 | P16: 0.034 | Q16: 15.2 | R16: 4 | S16: 108 | T16: 44 | U16: 25.2 | V16: 653940 | W16: 60 | X16: 60 | Y16: 4 | Z16: 4 | AA16: 1018 | AB16: 30 | AC16: 30 | AD16: 15 | AE16: 1013607 | AF16: 948213 | AG16: 82000 | AH16: 650000 | AI16: 4.15 | AJ16: 300000 | AK16: =D16+E16+K16-G16-H16 | AL16: =IF(AK16=D16+E16+K16-G16-H16,"平衡","不平衡") | AM16: =IF(Z16=Y16,"一致","不一致")
A17: 12月 | B17: =C16 | C17: 1020 | D17: =AK16 | E17: 32 | F17: 0 | G17: 28 | H17: 5 | I17: 868 | J17: 152 | K17: 90 | L17: 86 | M17: 970000 | N17: 955450 | O17: 0.0408 | P17: 0.0345 | Q17: 14.8 | R17: 3.8 | S17: 115 | T17: 48 | U17: 25.5 | V17: 686154 | W17: 62 | X17: 62 | Y17: 5 | Z17: 5 | AA17: 1020 | AB17: 31 | AC17: 31 | AD17: 14 | AE17: 1063539 | AF17: 994923 | AG17: 80000 | AH17: 650000 | AI17: 4.2 | AJ17: 336000 | AK17: =D17+E17+K17-G17-H17 | AL17: =IF(AK17=D17+E17+K17-G17-H17,"平衡","不平衡") | AM17: =IF(Z17=Y17,"一致","不一致")

Sheet ④演算-指标计算
A1: ④ 月度奶牛核心指标计算（公式引用③录入区，实时动态演算）
A2: 全部指标由公式自动重算；红底单元格标示触发行业预警（体细胞数SCC>20万/mL、成母牛死亡率>0.8%等）。
A3: 月份 | B3: 平均成母牛 | C3: 平均泌乳牛 | D3: 泌乳牛比例 | E3: 月总产奶(吨) | F3: 泌乳牛日均单产(kg) | G3: 生鲜牛乳脂率 | H3: 体细胞数(万/mL) | I3: 情期受胎率 | J3: 料奶比(FMR) | K3: 犊牛成活率 | L3: 临床乳房炎发病率 | M3: 成母牛月死亡率 | N3: 休药期合规率 | O3: 无害化处理率 | P3: 公斤奶总成本(元) | Q3: 公斤奶饲料成本(元) | R3: 公斤奶净盈利(元) | S3: 月度头均利润(元)
A6: ='③演算-数据录入'!A6 | B6: =('③演算-数据录入'!B6+'③演算-数据录入'!C6)/2 | C6: ='③演算-数据录入'!I6 | D6: =C6/B6 | E6: ='③演算-数据录入'!M6/1000 | F6: ='③演算-数据录入'!M6/C6/'③演算-数据录入'!AB6 | G6: ='③演算-数据录入'!O6 | H6: ='③演算-数据录入'!Q6 | I6: ='③演算-数据录入'!T6/'③演算-数据录入'!S6 | J6: ='③演算-数据录入'!V6/'③演算-数据录入'!M6 | K6: ='③演算-数据录入'!L6/'③演算-数据录入'!K6 | L6: ='③演算-数据录入'!AD6/C6 | M6: ='③演算-数据录入'!H6/B6 | N6: ='③演算-数据录入'!X6/'③演算-数据录入'!W6 | O6: ='③演算-数据录入'!Z6/'③演算-数据录入'!Y6 | P6: =('③演算-数据录入'!AE6+'③演算-数据录入'!AF6+'③演算-数据录入'!AG6+'③演算-数据录入'!AH6)/'③演算-数据录入'!M6 | Q6: =('③演算-数据录入'!AE6+'③演算-数据录入'!AF6)/'③演算-数据录入'!M6 | R6: ='③演算-数据录入'!AI6-P6 | S6: =R6*'③演算-数据录入'!M6/B6
A7: ='③演算-数据录入'!A7 | B7: =('③演算-数据录入'!B7+'③演算-数据录入'!C7)/2 | C7: ='③演算-数据录入'!I7 | D7: =C7/B7 | E7: ='③演算-数据录入'!M7/1000 | F7: ='③演算-数据录入'!M7/C7/'③演算-数据录入'!AB7 | G7: ='③演算-数据录入'!O7 | H7: ='③演算-数据录入'!Q7 | I7: ='③演算-数据录入'!T7/'③演算-数据录入'!S7 | J7: ='③演算-数据录入'!V7/'③演算-数据录入'!M7 | K7: ='③演算-数据录入'!L7/'③演算-数据录入'!K7 | L7: ='③演算-数据录入'!AD7/C7 | M7: ='③演算-数据录入'!H7/B7 | N7: ='③演算-数据录入'!X7/'③演算-数据录入'!W7 | O7: ='③演算-数据录入'!Z7/'③演算-数据录入'!Y7 | P7: =('③演算-数据录入'!AE7+'③演算-数据录入'!AF7+'③演算-数据录入'!AG7+'③演算-数据录入'!AH7)/'③演算-数据录入'!M7 | Q7: =('③演算-数据录入'!AE7+'③演算-数据录入'!AF7)/'③演算-数据录入'!M7 | R7: ='③演算-数据录入'!AI7-P7 | S7: =R7*'③演算-数据录入'!M7/B7
A8: ='③演算-数据录入'!A8 | B8: =('③演算-数据录入'!B8+'③演算-数据录入'!C8)/2 | C8: ='③演算-数据录入'!I8 | D8: =C8/B8 | E8: ='③演算-数据录入'!M8/1000 | F8: ='③演算-数据录入'!M8/C8/'③演算-数据录入'!AB8 | G8: ='③演算-数据录入'!O8 | H8: ='③演算-数据录入'!Q8 | I8: ='③演算-数据录入'!T8/'③演算-数据录入'!S8 | J8: ='③演算-数据录入'!V8/'③演算-数据录入'!M8 | K8: ='③演算-数据录入'!L8/'③演算-数据录入'!K8 | L8: ='③演算-数据录入'!AD8/C8 | M8: ='③演算-数据录入'!H8/B8 | N8: ='③演算-数据录入'!X8/'③演算-数据录入'!W8 | O8: ='③演算-数据录入'!Z8/'③演算-数据录入'!Y8 | P8: =('③演算-数据录入'!AE8+'③演算-数据录入'!AF8+'③演算-数据录入'!AG8+'③演算-数据录入'!AH8)/'③演算-数据录入'!M8 | Q8: =('③演算-数据录入'!AE8+'③演算-数据录入'!AF8)/'③演算-数据录入'!M8 | R8: ='③演算-数据录入'!AI8-P8 | S8: =R8*'③演算-数据录入'!M8/B8
A9: ='③演算-数据录入'!A9 | B9: =('③演算-数据录入'!B9+'③演算-数据录入'!C9)/2 | C9: ='③演算-数据录入'!I9 | D9: =C9/B9 | E9: ='③演算-数据录入'!M9/1000 | F9: ='③演算-数据录入'!M9/C9/'③演算-数据录入'!AB9 | G9: ='③演算-数据录入'!O9 | H9: ='③演算-数据录入'!Q9 | I9: ='③演算-数据录入'!T9/'③演算-数据录入'!S9 | J9: ='③演算-数据录入'!V9/'③演算-数据录入'!M9 | K9: ='③演算-数据录入'!L9/'③演算-数据录入'!K9 | L9: ='③演算-数据录入'!AD9/C9 | M9: ='③演算-数据录入'!H9/B9 | N9: ='③演算-数据录入'!X9/'③演算-数据录入'!W9 | O9: ='③演算-数据录入'!Z9/'③演算-数据录入'!Y9 | P9: =('③演算-数据录入'!AE9+'③演算-数据录入'!AF9+'③演算-数据录入'!AG9+'③演算-数据录入'!AH9)/'③演算-数据录入'!M9 | Q9: =('③演算-数据录入'!AE9+'③演算-数据录入'!AF9)/'③演算-数据录入'!M9 | R9: ='③演算-数据录入'!AI9-P9 | S9: =R9*'③演算-数据录入'!M9/B9
A10: ='③演算-数据录入'!A10 | B10: =('③演算-数据录入'!B10+'③演算-数据录入'!C10)/2 | C10: ='③演算-数据录入'!I10 | D10: =C10/B10 | E10: ='③演算-数据录入'!M10/1000 | F10: ='③演算-数据录入'!M10/C10/'③演算-数据录入'!AB10 | G10: ='③演算-数据录入'!O10 | H10: ='③演算-数据录入'!Q10 | I10: ='③演算-数据录入'!T10/'③演算-数据录入'!S10 | J10: ='③演算-数据录入'!V10/'③演算-数据录入'!M10 | K10: ='③演算-数据录入'!L10/'③演算-数据录入'!K10 | L10: ='③演算-数据录入'!AD10/C10 | M10: ='③演算-数据录入'!H10/B10 | N10: ='③演算-数据录入'!X10/'③演算-数据录入'!W10 | O10: ='③演算-数据录入'!Z10/'③演算-数据录入'!Y10 | P10: =('③演算-数据录入'!AE10+'③演算-数据录入'!AF10+'③演算-数据录入'!AG10+'③演算-数据录入'!AH10)/'③演算-数据录入'!M10 | Q10: =('③演算-数据录入'!AE10+'③演算-数据录入'!AF10)/'③演算-数据录入'!M10 | R10: ='③演算-数据录入'!AI10-P10 | S10: =R10*'③演算-数据录入'!M10/B10
A11: ='③演算-数据录入'!A11 | B11: =('③演算-数据录入'!B11+'③演算-数据录入'!C11)/2 | C11: ='③演算-数据录入'!I11 | D11: =C11/B11 | E11: ='③演算-数据录入'!M11/1000 | F11: ='③演算-数据录入'!M11/C11/'③演算-数据录入'!AB11 | G11: ='③演算-数据录入'!O11 | H11: ='③演算-数据录入'!Q11 | I11: ='③演算-数据录入'!T11/'③演算-数据录入'!S11 | J11: ='③演算-数据录入'!V11/'③演算-数据录入'!M11 | K11: ='③演算-数据录入'!L11/'③演算-数据录入'!K11 | L11: ='③演算-数据录入'!AD11/C11 | M11: ='③演算-数据录入'!H11/B11 | N11: ='③演算-数据录入'!X11/'③演算-数据录入'!W11 | O11: ='③演算-数据录入'!Z11/'③演算-数据录入'!Y11 | P11: =('③演算-数据录入'!AE11+'③演算-数据录入'!AF11+'③演算-数据录入'!AG11+'③演算-数据录入'!AH11)/'③演算-数据录入'!M11 | Q11: =('③演算-数据录入'!AE11+'③演算-数据录入'!AF11)/'③演算-数据录入'!M11 | R11: ='③演算-数据录入'!AI11-P11 | S11: =R11*'③演算-数据录入'!M11/B11
A12: ='③演算-数据录入'!A12 | B12: =('③演算-数据录入'!B12+'③演算-数据录入'!C12)/2 | C12: ='③演算-数据录入'!I12 | D12: =C12/B12 | E12: ='③演算-数据录入'!M12/1000 | F12: ='③演算-数据录入'!M12/C12/'③演算-数据录入'!AB12 | G12: ='③演算-数据录入'!O12 | H12: ='③演算-数据录入'!Q12 | I12: ='③演算-数据录入'!T12/'③演算-数据录入'!S12 | J12: ='③演算-数据录入'!V12/'③演算-数据录入'!M12 | K12: ='③演算-数据录入'!L12/'③演算-数据录入'!K12 | L12: ='③演算-数据录入'!AD12/C12 | M12: ='③演算-数据录入'!H12/B12 | N12: ='③演算-数据录入'!X12/'③演算-数据录入'!W12 | O12: ='③演算-数据录入'!Z12/'③演算-数据录入'!Y12 | P12: =('③演算-数据录入'!AE12+'③演算-数据录入'!AF12+'③演算-数据录入'!AG12+'③演算-数据录入'!AH12)/'③演算-数据录入'!M12 | Q12: =('③演算-数据录入'!AE12+'③演算-数据录入'!AF12)/'③演算-数据录入'!M12 | R12: ='③演算-数据录入'!AI12-P12 | S12: =R12*'③演算-数据录入'!M12/B12
A13: ='③演算-数据录入'!A13 | B13: =('③演算-数据录入'!B13+'③演算-数据录入'!C13)/2 | C13: ='③演算-数据录入'!I13 | D13: =C13/B13 | E13: ='③演算-数据录入'!M13/1000 | F13: ='③演算-数据录入'!M13/C13/'③演算-数据录入'!AB13 | G13: ='③演算-数据录入'!O13 | H13: ='③演算-数据录入'!Q13 | I13: ='③演算-数据录入'!T13/'③演算-数据录入'!S13 | J13: ='③演算-数据录入'!V13/'③演算-数据录入'!M13 | K13: ='③演算-数据录入'!L13/'③演算-数据录入'!K13 | L13: ='③演算-数据录入'!AD13/C13 | M13: ='③演算-数据录入'!H13/B13 | N13: ='③演算-数据录入'!X13/'③演算-数据录入'!W13 | O13: ='③演算-数据录入'!Z13/'③演算-数据录入'!Y13 | P13: =('③演算-数据录入'!AE13+'③演算-数据录入'!AF13+'③演算-数据录入'!AG13+'③演算-数据录入'!AH13)/'③演算-数据录入'!M13 | Q13: =('③演算-数据录入'!AE13+'③演算-数据录入'!AF13)/'③演算-数据录入'!M13 | R13: ='③演算-数据录入'!AI13-P13 | S13: =R13*'③演算-数据录入'!M13/B13
A14: ='③演算-数据录入'!A14 | B14: =('③演算-数据录入'!B14+'③演算-数据录入'!C14)/2 | C14: ='③演算-数据录入'!I14 | D14: =C14/B14 | E14: ='③演算-数据录入'!M14/1000 | F14: ='③演算-数据录入'!M14/C14/'③演算-数据录入'!AB14 | G14: ='③演算-数据录入'!O14 | H14: ='③演算-数据录入'!Q14 | I14: ='③演算-数据录入'!T14/'③演算-数据录入'!S14 | J14: ='③演算-数据录入'!V14/'③演算-数据录入'!M14 | K14: ='③演算-数据录入'!L14/'③演算-数据录入'!K14 | L14: ='③演算-数据录入'!AD14/C14 | M14: ='③演算-数据录入'!H14/B14 | N14: ='③演算-数据录入'!X14/'③演算-数据录入'!W14 | O14: ='③演算-数据录入'!Z14/'③演算-数据录入'!Y14 | P14: =('③演算-数据录入'!AE14+'③演算-数据录入'!AF14+'③演算-数据录入'!AG14+'③演算-数据录入'!AH14)/'③演算-数据录入'!M14 | Q14: =('③演算-数据录入'!AE14+'③演算-数据录入'!AF14)/'③演算-数据录入'!M14 | R14: ='③演算-数据录入'!AI14-P14 | S14: =R14*'③演算-数据录入'!M14/B14
A15: ='③演算-数据录入'!A15 | B15: =('③演算-数据录入'!B15+'③演算-数据录入'!C15)/2 | C15: ='③演算-数据录入'!I15 | D15: =C15/B15 | E15: ='③演算-数据录入'!M15/1000 | F15: ='③演算-数据录入'!M15/C15/'③演算-数据录入'!AB15 | G15: ='③演算-数据录入'!O15 | H15: ='③演算-数据录入'!Q15 | I15: ='③演算-数据录入'!T15/'③演算-数据录入'!S15 | J15: ='③演算-数据录入'!V15/'③演算-数据录入'!M15 | K15: ='③演算-数据录入'!L15/'③演算-数据录入'!K15 | L15: ='③演算-数据录入'!AD15/C15 | M15: ='③演算-数据录入'!H15/B15 | N15: ='③演算-数据录入'!X15/'③演算-数据录入'!W15 | O15: ='③演算-数据录入'!Z15/'③演算-数据录入'!Y15 | P15: =('③演算-数据录入'!AE15+'③演算-数据录入'!AF15+'③演算-数据录入'!AG15+'③演算-数据录入'!AH15)/'③演算-数据录入'!M15 | Q15: =('③演算-数据录入'!AE15+'③演算-数据录入'!AF15)/'③演算-数据录入'!M15 | R15: ='③演算-数据录入'!AI15-P15 | S15: =R15*'③演算-数据录入'!M15/B15
A16: ='③演算-数据录入'!A16 | B16: =('③演算-数据录入'!B16+'③演算-数据录入'!C16)/2 | C16: ='③演算-数据录入'!I16 | D16: =C16/B16 | E16: ='③演算-数据录入'!M16/1000 | F16: ='③演算-数据录入'!M16/C16/'③演算-数据录入'!AB16 | G16: ='③演算-数据录入'!O16 | H16: ='③演算-数据录入'!Q16 | I16: ='③演算-数据录入'!T16/'③演算-数据录入'!S16 | J16: ='③演算-数据录入'!V16/'③演算-数据录入'!M16 | K16: ='③演算-数据录入'!L16/'③演算-数据录入'!K16 | L16: ='③演算-数据录入'!AD16/C16 | M16: ='③演算-数据录入'!H16/B16 | N16: ='③演算-数据录入'!X16/'③演算-数据录入'!W16 | O16: ='③演算-数据录入'!Z16/'③演算-数据录入'!Y16 | P16: =('③演算-数据录入'!AE16+'③演算-数据录入'!AF16+'③演算-数据录入'!AG16+'③演算-数据录入'!AH16)/'③演算-数据录入'!M16 | Q16: =('③演算-数据录入'!AE16+'③演算-数据录入'!AF16)/'③演算-数据录入'!M16 | R16: ='③演算-数据录入'!AI16-P16 | S16: =R16*'③演算-数据录入'!M16/B16
A17: ='③演算-数据录入'!A17 | B17: =('③演算-数据录入'!B17+'③演算-数据录入'!C17)/2 | C17: ='③演算-数据录入'!I17 | D17: =C17/B17 | E17: ='③演算-数据录入'!M17/1000 | F17: ='③演算-数据录入'!M17/C17/'③演算-数据录入'!AB17 | G17: ='③演算-数据录入'!O17 | H17: ='③演算-数据录入'!Q17 | I17: ='③演算-数据录入'!T17/'③演算-数据录入'!S17 | J17: ='③演算-数据录入'!V17/'③演算-数据录入'!M17 | K17: ='③演算-数据录入'!L17/'③演算-数据录入'!K17 | L17: ='③演算-数据录入'!AD17/C17 | M17: ='③演算-数据录入'!H17/B17 | N17: ='③演算-数据录入'!X17/'③演算-数据录入'!W17 | O17: ='③演算-数据录入'!Z17/'③演算-数据录入'!Y17 | P17: =('③演算-数据录入'!AE17+'③演算-数据录入'!AF17+'③演算-数据录入'!AG17+'③演算-数据录入'!AH17)/'③演算-数据录入'!M17 | Q17: =('③演算-数据录入'!AE17+'③演算-数据录入'!AF17)/'③演算-数据录入'!M17 | R17: ='③演算-数据录入'!AI17-P17 | S17: =R17*'③演算-数据录入'!M17/B17
A20: 年度综合KPI与行业基准断言
A21: 年度核心指标 | B21: 单位 | C21: 年化测算值 | D21: 行业基准下限 | E21: 行业基准上限 | F21: 优秀/目标值 | G21: 判定规则 | H21: 断言结果
A22: 成母牛年单产(305天) | B22: kg | C22: =SUM('③演算-数据录入'!M6:M17)/AVERAGE(B6:B17) | D22: 9500 | E22: 12000 | F22: 11500 | G22: 低于下限=异常；达到目标=优秀 | H22: =IF(ISNUMBER(D22),IF(C22<D22,"异常",IF(AND(ISNUMBER(F22),C22>=F22),"优秀","达标")),"")
A23: 泌乳牛日均单产 | B23: kg | C23: =AVERAGE(F6:F17) | D23: 30 | E23: 38 | F23: 35 | G23: 低于下限=异常；达到目标=优秀 | H23: =IF(ISNUMBER(D23),IF(C23<D23,"异常",IF(AND(ISNUMBER(F23),C23>=F23),"优秀","达标")),"")
A24: 生鲜牛乳脂率 | B24: % | C24: =AVERAGE(G6:G17) | D24: 0.037 | E24: 0.042 | F24: 0.0395 | G24: 落在区间=达标；达到目标=优秀 | H24: =IF(OR(C24<D24,C24>E24),"异常",IF(AND(ISNUMBER(F24),C24>=F24),"优秀","达标"))
A25: 生鲜牛乳蛋白率 | B25: % | C25: =AVERAGE('③演算-数据录入'!P6:'③演算-数据录入'!P17) | D25: 0.031 | E25: 0.035 | F25: 0.0335 | G25: 落在区间=达标；达到目标=优秀 | H25: =IF(OR(C25<D25,C25>E25),"异常",IF(AND(ISNUMBER(F25),C25>=F25),"优秀","达标"))
A26: 体细胞数 SCC均值 | B26: 万/mL | C26: =AVERAGE(H6:H17) | E26: 20 | F26: 15 | G26: 超过上限=异常；达到目标=优秀 | H26: =IF(ISNUMBER(E26),IF(C26>E26,"异常",IF(AND(ISNUMBER(F26),C26<=F26),"优秀","达标")),"")
A27: 年化料奶比(FMR) | B27: :1 | C27: =(SUM('③演算-数据录入'!AE6:AE17)+SUM('③演算-数据录入'!AF6:AF17))/SUM('③演算-数据录入'!M6:M17)*0.4 | D27: 1.35 | E27: 1.65 | F27: 1.45 | G27: 超过上限=异常；达到目标=优秀 | H27: =IF(ISNUMBER(E27),IF(C27>E27,"异常",IF(AND(ISNUMBER(F27),C27<=F27),"优秀","达标")),"")
A28: 情期受胎率 | B28: % | C28: =SUM('③演算-数据录入'!T6:T17)/SUM('③演算-数据录入'!S6:S17) | D28: 0.35 | E28: 0.45 | F28: 0.4 | G28: 低于下限=异常；达到目标=优秀 | H28: =IF(ISNUMBER(D28),IF(C28<D28,"异常",IF(AND(ISNUMBER(F28),C28>=F28),"优秀","达标")),"")
A29: 犊牛成活率 | B29: % | C29: =SUM('③演算-数据录入'!L6:L17)/SUM('③演算-数据录入'!K6:K17) | D29: 0.95 | E29: 0.98 | F29: 0.96 | G29: 低于下限=异常；达到目标=优秀 | H29: =IF(ISNUMBER(D29),IF(C29<D29,"异常",IF(AND(ISNUMBER(F29),C29>=F29),"优秀","达标")),"")
A30: 成母牛年死淘率 | B30: % | C30: =(SUM('③演算-数据录入'!G6:G17)+SUM('③演算-数据录入'!H6:H17))/AVERAGE(B6:B17) | D30: 0.25 | E30: 0.32 | F30: 0.28 | G30: 落在区间=达标；达到目标=优秀 | H30: =IF(OR(C30<D30,C30>E30),"异常",IF(AND(ISNUMBER(F30),C30>=F30),"优秀","达标"))
A31: 成母牛月均死亡率 | B31: % | C31: =AVERAGE(M6:M17) | E31: 0.008 | F31: 0.005 | G31: 超过上限=异常；达到目标=优秀 | H31: =IF(ISNUMBER(E31),IF(C31>E31,"异常",IF(AND(ISNUMBER(F31),C31<=F31),"优秀","达标")),"")
A32: 休药期弃奶合规率 | B32: % | C32: =SUM('③演算-数据录入'!X6:X17)/SUM('③演算-数据录入'!W6:W17) | F32: 1 | G32: 达到目标=达标，否则异常 | H32: =IF(C32>=F32,"达标","异常")
A33: 病死牛无害化处理率 | B33: % | C33: =SUM('③演算-数据录入'!Z6:Z17)/SUM('③演算-数据录入'!Y6:Y17) | F33: 1 | G33: 达到目标=达标，否则异常 | H33: =IF(C33>=F33,"达标","异常")
A34: 耳标佩戴率 | B34: % | C34: =AVERAGE('③演算-数据录入'!AA6:AA17)/AVERAGE(B6:B17) | F34: 1 | G34: 达到目标=达标，否则异常 | H34: =IF(C34>=F34,"达标","异常")
A35: 公斤奶总成本 | B35: 元/kg | C35: =(SUM('③演算-数据录入'!AE6:AE17)+SUM('③演算-数据录入'!AF6:AF17)+SUM('③演算-数据录入'!AG6:AG17)+SUM('③演算-数据录入'!AH6:AH17))/SUM('③演算-数据录入'!M6:M17) | D35: 3.2 | E35: 3.8 | F35: 3.4 | G35: 行业行情参考，不设硬性判定 | H35: =""
A36: 公斤奶饲料成本 | B36: 元/kg | C36: =(SUM('③演算-数据录入'!AE6:AE17)+SUM('③演算-数据录入'!AF6:AF17))/SUM('③演算-数据录入'!M6:M17) | D36: 2.1 | E36: 2.5 | F36: 2.25 | G36: 行业行情参考，不设硬性判定 | H36: =""
A37: 公斤奶平均售价 | B37: 元/kg | C37: =SUMPRODUCT('③演算-数据录入'!M6:M17,'③演算-数据录入'!AI6:AI17)/SUM('③演算-数据录入'!M6:M17) | D37: 3.7 | E37: 4.4 | F37: 4.1 | G37: 行业行情参考，不设硬性判定 | H37: =""
A38: 成母牛头均年净利润 | B38: 元/头 | C38: =SUM(S6:S17) | D38: 2500 | E38: 6000 | F38: 4500 | G38: 低于下限=异常；达到目标=优秀 | H38: =IF(ISNUMBER(D38),IF(C38<D38,"异常",IF(AND(ISNUMBER(F38),C38>=F38),"优秀","达标")),"")

Sheet ⑤可视化数据准备
A1: ⑤ 奶牛可视化数据准备（月度标准宽表 · 直接驱动大屏看板）
A2: 本表结构为大屏看板直驱宽表：单产走势、乳品质变化、体细胞数预警线、饲喂成本与公斤奶利润分析。
A4: 月份 | B4: 平均成母牛 | C4: 泌乳牛日均单产(kg) | D4: 月总产奶(吨) | E4: 生鲜牛乳脂率 | F4: 生鲜牛乳蛋白率 | G4: 体细胞数(万/mL) | H4: 料奶比(FMR) | I4: 犊牛成活率 | J4: 成母牛月死亡率 | K4: 公斤奶总成本(元) | L4: 公斤奶售价(元) | M4: 公斤奶净利润(元) | N4: 头均月利润(元)
A5: ='④演算-指标计算'!A6 | B5: ='④演算-指标计算'!B6 | C5: ='④演算-指标计算'!F6 | D5: ='④演算-指标计算'!E6 | E5: ='④演算-指标计算'!G6 | F5: ='③演算-数据录入'!P6 | G5: ='④演算-指标计算'!H6 | H5: ='④演算-指标计算'!J6 | I5: ='④演算-指标计算'!K6 | J5: ='④演算-指标计算'!M6 | K5: ='④演算-指标计算'!P6 | L5: ='③演算-数据录入'!AI6 | M5: ='④演算-指标计算'!R6 | N5: ='④演算-指标计算'!S6
A6: ='④演算-指标计算'!A7 | B6: ='④演算-指标计算'!B7 | C6: ='④演算-指标计算'!F7 | D6: ='④演算-指标计算'!E7 | E6: ='④演算-指标计算'!G7 | F6: ='③演算-数据录入'!P7 | G6: ='④演算-指标计算'!H7 | H6: ='④演算-指标计算'!J7 | I6: ='④演算-指标计算'!K7 | J6: ='④演算-指标计算'!M7 | K6: ='④演算-指标计算'!P7 | L6: ='③演算-数据录入'!AI7 | M6: ='④演算-指标计算'!R7 | N6: ='④演算-指标计算'!S7
A7: ='④演算-指标计算'!A8 | B7: ='④演算-指标计算'!B8 | C7: ='④演算-指标计算'!F8 | D7: ='④演算-指标计算'!E8 | E7: ='④演算-指标计算'!G8 | F7: ='③演算-数据录入'!P8 | G7: ='④演算-指标计算'!H8 | H7: ='④演算-指标计算'!J8 | I7: ='④演算-指标计算'!K8 | J7: ='④演算-指标计算'!M8 | K7: ='④演算-指标计算'!P8 | L7: ='③演算-数据录入'!AI8 | M7: ='④演算-指标计算'!R8 | N7: ='④演算-指标计算'!S8
A8: ='④演算-指标计算'!A9 | B8: ='④演算-指标计算'!B9 | C8: ='④演算-指标计算'!F9 | D8: ='④演算-指标计算'!E9 | E8: ='④演算-指标计算'!G9 | F8: ='③演算-数据录入'!P9 | G8: ='④演算-指标计算'!H9 | H8: ='④演算-指标计算'!J9 | I8: ='④演算-指标计算'!K9 | J8: ='④演算-指标计算'!M9 | K8: ='④演算-指标计算'!P9 | L8: ='③演算-数据录入'!AI9 | M8: ='④演算-指标计算'!R9 | N8: ='④演算-指标计算'!S9
A9: ='④演算-指标计算'!A10 | B9: ='④演算-指标计算'!B10 | C9: ='④演算-指标计算'!F10 | D9: ='④演算-指标计算'!E10 | E9: ='④演算-指标计算'!G10 | F9: ='③演算-数据录入'!P10 | G9: ='④演算-指标计算'!H10 | H9: ='④演算-指标计算'!J10 | I9: ='④演算-指标计算'!K10 | J9: ='④演算-指标计算'!M10 | K9: ='④演算-指标计算'!P10 | L9: ='③演算-数据录入'!AI10 | M9: ='④演算-指标计算'!R10 | N9: ='④演算-指标计算'!S10
A10: ='④演算-指标计算'!A11 | B10: ='④演算-指标计算'!B11 | C10: ='④演算-指标计算'!F11 | D10: ='④演算-指标计算'!E11 | E10: ='④演算-指标计算'!G11 | F10: ='③演算-数据录入'!P11 | G10: ='④演算-指标计算'!H11 | H10: ='④演算-指标计算'!J11 | I10: ='④演算-指标计算'!K11 | J10: ='④演算-指标计算'!M11 | K10: ='④演算-指标计算'!P11 | L10: ='③演算-数据录入'!AI11 | M10: ='④演算-指标计算'!R11 | N10: ='④演算-指标计算'!S11
A11: ='④演算-指标计算'!A12 | B11: ='④演算-指标计算'!B12 | C11: ='④演算-指标计算'!F12 | D11: ='④演算-指标计算'!E12 | E11: ='④演算-指标计算'!G12 | F11: ='③演算-数据录入'!P12 | G11: ='④演算-指标计算'!H12 | H11: ='④演算-指标计算'!J12 | I11: ='④演算-指标计算'!K12 | J11: ='④演算-指标计算'!M12 | K11: ='④演算-指标计算'!P12 | L11: ='③演算-数据录入'!AI12 | M11: ='④演算-指标计算'!R12 | N11: ='④演算-指标计算'!S12
A12: ='④演算-指标计算'!A13 | B12: ='④演算-指标计算'!B13 | C12: ='④演算-指标计算'!F13 | D12: ='④演算-指标计算'!E13 | E12: ='④演算-指标计算'!G13 | F12: ='③演算-数据录入'!P13 | G12: ='④演算-指标计算'!H13 | H12: ='④演算-指标计算'!J13 | I12: ='④演算-指标计算'!K13 | J12: ='④演算-指标计算'!M13 | K12: ='④演算-指标计算'!P13 | L12: ='③演算-数据录入'!AI13 | M12: ='④演算-指标计算'!R13 | N12: ='④演算-指标计算'!S13
A13: ='④演算-指标计算'!A14 | B13: ='④演算-指标计算'!B14 | C13: ='④演算-指标计算'!F14 | D13: ='④演算-指标计算'!E14 | E13: ='④演算-指标计算'!G14 | F13: ='③演算-数据录入'!P14 | G13: ='④演算-指标计算'!H14 | H13: ='④演算-指标计算'!J14 | I13: ='④演算-指标计算'!K14 | J13: ='④演算-指标计算'!M14 | K13: ='④演算-指标计算'!P14 | L13: ='③演算-数据录入'!AI14 | M13: ='④演算-指标计算'!R14 | N13: ='④演算-指标计算'!S14
A14: ='④演算-指标计算'!A15 | B14: ='④演算-指标计算'!B15 | C14: ='④演算-指标计算'!F15 | D14: ='④演算-指标计算'!E15 | E14: ='④演算-指标计算'!G15 | F14: ='③演算-数据录入'!P15 | G14: ='④演算-指标计算'!H15 | H14: ='④演算-指标计算'!J15 | I14: ='④演算-指标计算'!K15 | J14: ='④演算-指标计算'!M15 | K14: ='④演算-指标计算'!P15 | L14: ='③演算-数据录入'!AI15 | M14: ='④演算-指标计算'!R15 | N14: ='④演算-指标计算'!S15
A15: ='④演算-指标计算'!A16 | B15: ='④演算-指标计算'!B16 | C15: ='④演算-指标计算'!F16 | D15: ='④演算-指标计算'!E16 | E15: ='④演算-指标计算'!G16 | F15: ='③演算-数据录入'!P16 | G15: ='④演算-指标计算'!H16 | H15: ='④演算-指标计算'!J16 | I15: ='④演算-指标计算'!K16 | J15: ='④演算-指标计算'!M16 | K15: ='④演算-指标计算'!P16 | L15: ='③演算-数据录入'!AI16 | M15: ='④演算-指标计算'!R16 | N15: ='④演算-指标计算'!S16
A16: ='④演算-指标计算'!A17 | B16: ='④演算-指标计算'!B17 | C16: ='④演算-指标计算'!F17 | D16: ='④演算-指标计算'!E17 | E16: ='④演算-指标计算'!G17 | F16: ='③演算-数据录入'!P17 | G16: ='④演算-指标计算'!H17 | H16: ='④演算-指标计算'!J17 | I16: ='④演算-指标计算'!K17 | J16: ='④演算-指标计算'!M17 | K16: ='④演算-指标计算'!P17 | L16: ='③演算-数据录入'!AI17 | M16: ='④演算-指标计算'!R17 | N16: ='④演算-指标计算'!S17
A19: 年度奶牛核心KPI大数字卡片数据源
A20: 核心KPI | B20: 年化数值 | C20: 计量单位 | D20: 行业基准目标 | E20: 达成状态
A21: 成母牛年单产 | B21: ='④演算-指标计算'!C22 | C21: ='④演算-指标计算'!B22 | D21: ='④演算-指标计算'!F22 | E21: ='④演算-指标计算'!H22
A22: 泌乳牛日均单产 | B22: ='④演算-指标计算'!C23 | C22: ='④演算-指标计算'!B23 | D22: ='④演算-指标计算'!F23 | E22: ='④演算-指标计算'!H23
A23: 生鲜牛乳脂率 | B23: ='④演算-指标计算'!C24 | C23: ='④演算-指标计算'!B24 | D23: ='④演算-指标计算'!F24 | E23: ='④演算-指标计算'!H24
A24: 生鲜牛乳蛋白率 | B24: ='④演算-指标计算'!C25 | C24: ='④演算-指标计算'!B25 | D24: ='④演算-指标计算'!F25 | E24: ='④演算-指标计算'!H25
A25: 体细胞数 SCC | B25: ='④演算-指标计算'!C26 | C25: ='④演算-指标计算'!B26 | D25: ='④演算-指标计算'!F26 | E25: ='④演算-指标计算'!H26
A26: 年化料奶比 | B26: ='④演算-指标计算'!C27 | C26: ='④演算-指标计算'!B27 | D26: ='④演算-指标计算'!F27 | E26: ='④演算-指标计算'!H27
A27: 犊牛成活率 | B27: ='④演算-指标计算'!C29 | C27: ='④演算-指标计算'!B29 | D27: ='④演算-指标计算'!F29 | E27: ='④演算-指标计算'!H29
A28: 公斤奶平均成本 | B28: ='④演算-指标计算'!C35 | C28: ='④演算-指标计算'!B35 | D28: ='④演算-指标计算'!F35 | E28: ='④演算-指标计算'!H35
A29: 成母牛年头均净利润 | B29: ='④演算-指标计算'!C38 | C29: ='④演算-指标计算'!B38 | D29: ='④演算-指标计算'!F38 | E29: ='④演算-指标计算'!H38
