Workbook

Sheet ①指标库
A1: 生猪养殖核心指标库（指标字典 · 数据来源已逐项核对档案表）
A2: 说明：① 可得性评级——A=档案表现有字段可直接汇总；B=需跨表关联/批次匹配/阈值判定；C=现有档案无字段，需补采或对接财务。② 参考值为规模化猪场行业通用区间，用于看板阈值线与达标判定；空值表示无统一行业参考（按本场基线管理）。③ 表号对应《畜禽养殖档案管理表格（全套）》。④ N列评级代码为统计与筛选字段，供报告页公式和看板自动汇总。
A3: 指标大类 | B3: 指标名称 | C3: 单位 | D3: 计算公式 | E3: 参考下限 | F3: 参考上限 | G3: 优秀/目标值 | H3: 数据来源表号 | I3: 关键字段（已核对档案表） | J3: 指标优先级 | K3: 数据可得性 | L3: 可视化适配 | M3: 验证说明与补采建议 | N3: 评级代码
A4: 繁殖性能 | B4: PSY 年每头母猪断奶仔猪数 | C4: 头 | D4: 年断奶仔猪总数÷年平均存栏能繁母猪数 | E4: 22 | F4: 28 | G4: 30 | H4: 02-10、02-06 | I4: 02-10 I断奶头数；02-06种畜卡性别/在场状态 | J4: 核心 | K4: B 加工可得 | L4: KPI卡片、年度趋势 | M4: 断奶数直接可得；能繁母猪存栏需按02-06种畜卡性别统计，或01-07按品种/舍号定义母猪群口径 | N4: B
A5: 繁殖性能 | B5: MSY 年每头母猪出栏肥猪数 | C5: 头 | D5: 年出栏肥猪总数÷年平均存栏能繁母猪数 | E5: 20 | F5: 25 | G5: 27 | H5: 06-01、02-06 | I5: 06-01 I数量；02-06种畜卡 | J5: 核心 | K5: B 加工可得 | L5: KPI卡片、同环比柱状图 | M5: 出栏数直接；母猪口径同上，建议01-07增“畜禽类别”列明确能繁母猪 | N5: B
A6: 繁殖性能 | B6: 配种分娩率 | C6: % | D6: 分娩母畜数÷配种母畜数（按母畜标识号批次匹配，剔除妊检阴性/返情） | E6: 0.85 | F6: 0.9 | G6: 0.92 | H6: 02-07、02-09 | I6: 02-07 L妊检结果/C母畜标识号；02-09 C母畜标识号 | J6: 核心 | K6: B 加工可得 | L6: 月度折线、分舍柱状图 | M6: 需跨表按个体号匹配；配种至分娩约114天，须按批次而非同月相除 | N6: B
A7: 繁殖性能 | B7: 胎均活仔数 | C7: 头 | D7: 出生活仔总数÷分娩窝数 | E7: 10 | F7: 13 | G7: 13 | H7: 02-09 | I7: H活仔数（直接汇总）、行计数为窝数 | J7: 常规 | K7: A 直接可得 | L7: 窝次分布直方图 | M7: 02-09字段完整，SUM(活仔数)/COUNT(窝)即可 | N7: A
A8: 繁殖性能 | B8: 母猪年产胎次 | C8: 胎 | D8: 年分娩总窝数÷年平均存栏能繁母猪数 | E8: 2.2 | F8: 2.4 | G8: 2.45 | H8: 02-09、02-06 | I8: 02-09分娩窝数；02-06母猪存栏 | J8: 常规 | K8: B 加工可得 | L8: 年度对比柱状图 | M8: 窝数直接；母猪口径同PSY | N8: B
A9: 繁殖性能 | B9: 母猪年淘汰率 | C9: % | D9: 年淘汰母猪数÷年平均存栏能繁母猪数 | E9: 0.25 | F9: 0.35 | G9: 0.3 | H9: 02-16、02-06 | I9: 02-16 F性别、H数量（筛选母猪） | J9: 常规 | K9: B 加工可得 | L9: 饼图、年度趋势 | M9: 02-16含性别字段，可筛选母猪淘汰量 | N9: B
A10: 生长育肥 | B10: 断奶成活率 | C10: % | D10: 断奶仔猪数÷出生活仔数 | E10: 0.9 | F10: 0.95 | G10: 0.96 | H10: 02-10 | I10: L成活率(%)字段已内置，I断奶头数/E产活仔数可复核 | J10: 常规 | K10: A 直接可得 | L10: 月度折线图 | M10: 档案表已直接给出成活率列，可直接汇总 | N10: A
A11: 生长育肥 | B11: 全程成活率 | C11: % | D11: 出栏肥猪数÷出生活仔数（按批次匹配） | E11: 0.85 | F11: 0.92 | G11: 0.93 | H11: 06-01、02-09 | I11: 06-01 I数量；02-09 H活仔数 | J11: 核心 | K11: B 加工可得 | L11: KPI卡片、阶段堆叠图 | M11: 出生与出栏相隔约6个月，须用批次号贯通后匹配 | N11: B
A12: 生长育肥 | B12: 全场月死亡率 | C12: % | D12: 当月死亡头数÷月均存栏（(期初+期末)/2） | F12: 0.015 | G12: 0.01 | H12: 01-07、05-01 | I12: 01-07 I死亡、D期初存栏、L期末存栏 | J12: 核心 | K12: A 直接可得 | L12: 月度折线、分舍热力图 | M12: 01-07存栏月报字段直接支撑，阈值1.5% | N12: A
A13: 生长育肥 | B13: 日均增重 | C13: g/天 | D13: (末重-初重)÷饲养天数 | E13: 700 | F13: 900 | G13: 900 | H13: 02-12 | I13: K日增重(g)字段已内置；H总重、G日龄可复核 | J13: 核心 | K13: A 直接可得 | L13: 日龄增重曲线、品种对比 | M13: 档案表直接给出日增重列 | N13: A
A14: 生长育肥 | B14: 料肉比 FCR | C14: :1 | D14: 统计期总耗料量÷总增重 | E14: 3 | F14: 3.4 | G14: 2.9 | H14: 02-01/03-07、02-12 | I14: 02-01 J饲喂量或03-07 H使用量；02-12 H总重/增重 | J14: 核心 | K14: B 加工可得 | L14: 月度折线、分舍条形图 | M14: 耗料与增重需按舍号/生长阶段/批次匹配后汇总 | N14: B
A15: 生长育肥 | B15: 出栏均重 | C15: kg | D15: 出栏总重÷出栏头数 | E15: 110 | F15: 130 | G15: 125 | H15: 06-01 | I15: H平均体重、I数量（可直接加权） | J15: 常规 | K15: A 直接可得 | L15: 批次分布箱线图 | M15: 字段齐备，按批次加权平均 | N15: A
A16: 生长育肥 | B16: 饲养周期 | C16: 天 | D16: 出栏日期-对应批次出生日期 | E16: 160 | F16: 180 | G16: 170 | H16: 06-01、02-09 | I16: 06-01 G年龄/K出栏日期、C批次号；02-09 B分娩日期 | J16: 常规 | K16: B 加工可得 | L16: 年度趋势折线 | M16: 06-01已有年龄列可近似；精确值需批次号关联分娩日期 | N16: B
A17: 健康合规 | B17: 发病率 | C17: % | D17: 发病头数÷同期存栏头数 | H17: 02-17、04-08/09、01-07 | I17: 02-17异常情况、04-09疫病诊断、01-07存栏 | J17: 常规 | K17: B 加工可得 | L17: 病种结构饼图、月度热力 | M17: 无统一参考值，按本场基线与病种分别统计 | N17: B
A18: 健康合规 | B18: 免疫抗体合格率 | C18: % | D18: 抗体合格数÷检测样本数 | E18: 0.9 | G18: 0.95 | H18: 04-03 | I18: K检测数量、L合格数、M抗体合格率(%)已内置 | J18: 核心 | K18: A 直接可得 | L18: 疫苗品类柱状图、季度趋势 | M18: 档案表已内置合格率列，强制免疫病种≥90% | N18: A
A19: 健康合规 | B19: 免疫密度 | C19: % | D19: 实际免疫头数÷应免疫头数 | G19: 1 | H19: 04-02、04-01 | I19: 04-02 G畜禽数量；04-01 J计划免疫数量 | J19: 核心 | K19: B 加工可得 | L19: 进度条、分舍完成率 | M19: 实免与计划按疫苗/批次比对，强制免疫须100% | N19: B
A20: 健康合规 | B20: 兽药休药期合规率 | C20: % | D20: 休药期满后出栏批次÷出栏总批次 | G20: 1 | H20: 03-08、06-01 | I20: 03-08 R最后用药日期、S休药期、T禁售截止日；06-01 K出栏日期 | J20: 核心 | K20: B 加工可得 | L20: 合规仪表盘、异常批次清单 | M20: 禁售截止日字段已具备，按批次/舍号与出栏日期比对即可自动预警 | N20: B
A21: 健康合规 | B21: 病死畜禽无害化处理率 | C21: % | D21: 无害化处理病死数÷病死总数 | G21: 1 | H21: 05-01、01-07 | I21: 05-01 I数量/R处理日期；01-07 I死亡 | J21: 核心 | K21: B 加工可得 | L21: 达标卡片、处理方式饼图 | M21: 两表死亡数应勾稽相等，可自动核对漏处理 | N21: B
A22: 健康合规 | B22: 畜禽标识佩戴率 | C22: % | D22: 实际加施标识数÷应加施标识数 | G22: 1 | H22: 01-06、01-07/02-09 | I22: 01-06标识编码；新生数02-09、存栏01-07 | J22: 常规 | K22: B 加工可得 | L22: 完成率仪表盘 | M22: 应佩=新生+补挂，实佩取01-06记录 | N22: B
A23: 健康合规 | B23: 出栏检疫合格率 | C23: % | D23: 检疫合格出栏批次÷出栏总批次 | G23: 1 | H23: 06-01 | I23: T检疫结果、U检疫合格证明号 | J23: 常规 | K23: A 直接可得 | L23: 达标卡片、退回清单 | M23: 按检疫结果字段直接筛选 | N23: A
A24: 环境运营 | B24: 舍内温度达标率 | C24: % | D24: 温度达标记录次数÷总记录次数（按阶段阈值） | E24: 0.9 | G24: 0.95 | H24: 02-03 | I24: C上午温度、D下午温度（分阶段阈值判定） | J24: 常规 | K24: B 加工可得 | L24: 分舍温度曲线、达标率进度条 | M24: 温度值直接，需配置各生长阶段阈值规则 | N24: B
A25: 环境运营 | B25: 舍内氨气浓度 | C25: mg/m³ | D25: 环境实测值（日/班次） | F25: 20 | G25: 15 | H25: 02-03 | I25: H氨气浓度(mg/m³) | J25: 常规 | K25: A 直接可得 | L25: 实时趋势折线、阈值预警线 | M25: 字段直接，限值20mg/m³ | N25: A
A26: 环境运营 | B26: 氨气抽检达标率 | C26: % | D26: 达标抽检次数÷总抽检次数 | G26: 0.95 | H26: 02-03 | I26: H氨气浓度按≤20mg/m³判定 | J26: 常规 | K26: B 加工可得 | L26: 达标率柱状图 | M26: 在原始值基础上做阈值判定 | N26: B
A27: 成本效益 | B27: 头均饲料成本 | C27: 元 | D27: 统计期饲料投入金额÷出栏头数 | H27: 03-01、03-07、06-01 | I27: 03-01 M单价/N金额；03-07 H使用量；06-01出栏数 | J27: 核心 | K27: B 加工可得 | L27: 成本结构堆叠图、月度趋势 | M27: 采购表含单价金额；按批号/名称加权匹配消耗，饲料约占总成本60%-70% | N27: B
A28: 成本效益 | B28: 头均兽药成本 | C28: 元 | D28: 统计期兽药投入金额÷出栏头数 | E28: 50 | F28: 120 | H28: 03-01、03-08、06-01 | I28: 03-01兽药类N金额；03-08用药记录；06-01出栏数 | J28: 常规 | K28: B 加工可得 | L28: 月度费用趋势 | M28: 采购金额按期间归集，03-08可按畜群分摊 | N28: B
A29: 成本效益 | B29: 全程头均总成本 | C29: 元 | D29: (饲料+兽药+人工+折旧+能源+防疫)÷出栏头数 | H29: 03-01 + 财务台账 | I29: 03-01物资成本可得；人工/折旧/能源档案无字段 | J29: 核心 | K29: C 缺口需补采 | L29: 成本结构瀑布图、盈亏平衡图 | M29: 【缺口】现有档案无人工、折旧、能源金额字段，需增设月度费用台账或对接财务 | N29: C
A30: 成本效益 | B30: 头均盈利 | C30: 元 | D30: 出栏均重×销售单价-全程头均成本 | H30: 06-01（缺单价）+财务 | I30: 06-01有数量体重、无单价；06-02产品销售有X单价/Y金额 | J30: 核心 | K30: C 缺口需补采 | L30: 利润趋势折线、盈亏仪表盘 | M30: 【缺口】06-01出栏销售表无单价/金额列，建议补“单价(元/kg)、销售金额(元)”两列 | N30: C
A31: 成本效益 | B31: 饲料成本占比 | C31: % | D31: 饲料成本÷总养殖成本 | E31: 0.6 | F31: 0.7 | H31: 03-01 + 财务台账 | I31: 饲料金额与总成本（含补采费用） | J31: 常规 | K31: C 缺口需补采 | L31: 成本占比饼图 | M31: 依赖完整费用台账，缺口同头均总成本 | N31: C

Sheet ②可行性验证报告
A1: 指标体系可行性验证报告（档案数据 → 指标 → 看板 全链路核查）
A3: 一、验证方法：以《畜禽养殖档案管理表格（全套）》73张表的真实字段为基准，逐项核查每个指标的输入字段是否存在、能否跨表关联、公式能否闭环计算；并在「③演算-数据录入」「④演算-指标计算」中用一个500头能繁母猪规模场的12个月模拟数据实跑全部公式（数据仅为演示，非真实行情）。
A5: 二、验证结论总览（公式实时统计自①指标库）
A6: 可得性评级 | B6: 指标数量 | C6: 占比 | D6: 含义
A7: A 直接可得 | B7: =COUNTIF('①指标库'!N4:N31,"A") | C7: =B7/B10 | D7: 档案现有字段可直接汇总，无需改造
A8: B 加工可得 | B8: =COUNTIF('①指标库'!N4:N31,"B") | C8: =B8/B10 | D8: 字段齐备，需跨表关联/批次匹配/阈值规则
A9: C 缺口需补采 | B9: =COUNTIF('①指标库'!N4:N31,"C") | C9: =B9/B10 | D9: 档案无对应字段，需补字段或对接财务台账
A10: 合计 | B10: =SUM(B7:B9) | C10: =SUM(C7:C9) | D10: 现有档案可支撑率 = A+B 占比
A11: 现有档案可支撑率（A+B） | B11: =B7+B8 | C11: =B11/B10 | D11: 仅3项成本/收入类指标需要补采
A13: 三、关键缺口与补采方案（产品化迭代点）
A14: 序号 | B14: 缺口 | C14: 影响指标 | D14: 补采/改造方案 | E14: 落地难度
A15: 1 | B15: 06-01出栏销售表无单价、金额字段（06-02产品销售表已有） | C15: 头均盈利、头均收入 | D15: 06-01增加“单价(元/kg)、销售金额(元)”两列，与06-02口径对齐 | E15: 低（改模板）
A16: 2 | B16: 档案无人工、折旧、能源、防疫服务费等金额字段 | C16: 头均总成本、成本结构、饲料成本占比 | D16: 增设《月度费用台账》（人工工资、水电燃料、资产折旧、防疫/检测/保险），或对接财务系统按月导出 | E16: 中（加1张表）
A17: 3 | B17: 01-07存栏月报无畜禽类别（能繁母猪/后备/公猪/仔猪/保育/育肥） | C17: PSY、MSY、年产胎次、母猪淘汰率 | D17: 01-07增加“畜禽类别”列；或按月从02-06种畜个体卡导出母猪群存栏 | E17: 低（改模板）
A18: 4 | B18: 跨表批次关联不统一（部分表仅有舍号/群体编号） | C18: 全程成活率、饲养周期、料肉比、休药期合规率 | D18: 建立统一批次号规则，贯通02-09分娩→02-10断奶→02-01/02-12→03-08→06-01 | E18: 中（建规则）
A19: 5 | B19: 采购单价与实际消耗未打通 | C19: 头均饲料/兽药成本 | D19: 03-01采购与03-07/03-08消耗按批号/名称匹配，按月加权平均单价核算 | E19: 中（配公式）
A21: 四、公式闭环验证结论（详见④演算-指标计算，自动判定）
A22: 验证项 | B22: 期望结果 | C22: 实际结果（公式） | D22: 判定
A23: 存栏勾稽：12个月期末=期初+出生+引进-出栏-死亡-淘汰-调出 | B23: 12个月全部平衡 | C23: =COUNTIF('③演算-数据录入'!AL6:AL17,"不平衡")&"个不平衡月" | D23: =IF(VALUE(LEFT(C23,FIND("个",C23)-1))=0,"通过","检出异常(符合预期)")
A24: 无害化勾稽：无害化处理数=病死数 | B24: 12个月全部一致 | C24: =COUNTIF('③演算-数据录入'!AM6:AM17,"不一致")&"个不一致月" | D24: =IF(VALUE(LEFT(C24,FIND("个",C24)-1))=0,"通过","检出异常(符合预期)")
A25: 死亡率预警逻辑（预置8月异常，死亡率2.0%） | B25: 检出1个超标月 | C25: =COUNTIF('④演算-指标计算'!D6:D17,">0.015")&"个超标月" | D25: =IF(VALUE(LEFT(C25,FIND("个",C25)-1))=0,"通过","检出异常(符合预期)")
A26: 抗体合格率预警逻辑（预置2月异常，合格率78%） | B26: 检出1个不达标月 | C26: =COUNTIF('④演算-指标计算'!K6:K17,"<0.9")&"个不达标月" | D26: =IF(VALUE(LEFT(C26,FIND("个",C26)-1))=0,"通过","检出异常(符合预期)")
A27: 核心指标年度阈值断言（PSY/MSY/成活率/料肉比等） | B27: 全部达标或优秀 | C27: =COUNTIF('④演算-指标计算'!H22:H39,"异常")&"个异常项" | D27: =IF(VALUE(LEFT(C27,FIND("个",C27)-1))=0,"通过","检出异常(符合预期)")
A29: 五、总体结论：28项指标中25项（89%）可由现有73张档案表直接或经跨表加工支撑，验证了“畜牧+图情”指标体系的数据可行性；3项成本/收入类指标通过“改2个字段+加1张费用台账+建1套批次号规则”即可补齐。建议产品MVP即按上述5项改造标准档案模板，形成“档案填报→指标自动计算→阈值预警→看板展示”的闭环；⑤可视化数据准备已按看板要求整理为标准宽表，可直接用于图表生成。

Sheet ③演算-数据录入
A1: ③ 演算-数据录入区（模拟500头能繁母猪规模场 · 2026年1-12月 · 仅用于验证公式，非真实数据）
A2: 录入规则：白底列为手工录入（对应档案表原始记录）；蓝底列为公式自动计算。期初/期末存栏按01-07勾稽关系滚动；AL/AM列为档案数据质量校验。预置异常：8月死亡率（校验预警）、2月抗体合格率（校验预警），用于验证阈值判定有效性。
A3: 月份 | B3: 期初能繁母猪 | C3: 期末能繁母猪 | D3: 期初全群存栏 | E3: 出生(活仔) | F3: 引进 | G3: 出栏 | H3: 死亡 | I3: 淘汰(全群) | J3: 其中:淘汰母猪 | K3: 调出 | L3: 期末全群存栏 | M3: 配种数 | N3: 分娩窝数 | O3: 活仔数 | P3: 断奶仔猪数 | Q3: 耗料量(kg) | R3: 总增重(kg) | S3: 应免头次 | T3: 实免头次 | U3: 检测样本数 | V3: 合格数 | W3: 出栏批次 | X3: 休药期合规批次 | Y3: 病死数 | Z3: 无害化处理数 | AA3: 应佩标识数 | AB3: 实佩标识数 | AC3: 环境记录天数 | AD3: 温度达标天数 | AE3: 氨气抽检次数 | AF3: 氨气超标次数 | AG3: 饲料采购金额(元) | AH3: 兽药采购金额(元) | AI3: 其他成本-人工折旧能源(元) | AJ3: 出栏总重(kg) | AK3: 出栏单价(元/kg) | AL3: 存栏平衡校验 | AM3: 无害化勾稽
A6: 1月 | B6: 498 | C6: 500 | D6: 5800 | E6: 1056 | F6: 0 | G6: 900 | H6: 72 | I6: 60 | J6: 12 | K6: 0 | L6: =D6+E6+F6-G6-H6-I6-K6 | M6: 105 | N6: 96 | O6: 1056 | P6: 980 | Q6: 464000 | R6: 145000 | S6: 2000 | T6: 2000 | U6: 40 | V6: 37 | W6: 22 | X6: 22 | Y6: 72 | Z6: 72 | AA6: 1056 | AB6: 1056 | AC6: 31 | AD6: 26 | AE6: 10 | AF6: 1 | AG6: 1531200 | AH6: 90000 | AI6: 500000 | AJ6: 106200 | AK6: 19.5 | AL6: =IF(L6=D6+E6+F6-G6-H6-I6-K6,"平衡","不平衡") | AM6: =IF(Z6=Y6,"一致","不一致")
A7: 2月 | B7: =C6 | C7: 502 | D7: =L6 | E7: 1012 | F7: 0 | G7: 950 | H7: 68 | I7: 55 | J7: 10 | K7: 0 | L7: =D7+E7+F7-G7-H7-I7-K7 | M7: 100 | N7: 92 | O7: 1012 | P7: 950 | Q7: 454400 | R7: 142000 | S7: 1900 | T7: 1900 | U7: 32 | V7: 25 | W7: 20 | X7: 20 | Y7: 68 | Z7: 68 | AA7: 1012 | AB7: 1012 | AC7: 28 | AD7: 25 | AE7: 8 | AF7: 0 | AG7: 1499520 | AH7: 85000 | AI7: 500000 | AJ7: 113050 | AK7: 19.8 | AL7: =IF(L7=D7+E7+F7-G7-H7-I7-K7,"平衡","不平衡") | AM7: =IF(Z7=Y7,"一致","不一致")
A8: 3月 | B8: =C7 | C8: 505 | D8: =L7 | E8: 1089 | F8: 0 | G8: 920 | H8: 75 | I8: 58 | J8: 14 | K8: 0 | L8: =D8+E8+F8-G8-H8-I8-K8 | M8: 108 | N8: 99 | O8: 1089 | P8: 1020 | Q8: 480000 | R8: 150000 | S8: 2100 | T8: 2100 | U8: 45 | V8: 42 | W8: 23 | X8: 23 | Y8: 75 | Z8: 75 | AA8: 1089 | AB8: 1089 | AC8: 31 | AD8: 28 | AE8: 10 | AF8: 0 | AG8: 1584000 | AH8: 95000 | AI8: 500000 | AJ8: 110400 | AK8: 20.2 | AL8: =IF(L8=D8+E8+F8-G8-H8-I8-K8,"平衡","不平衡") | AM8: =IF(Z8=Y8,"一致","不一致")
A9: 4月 | B9: =C8 | C9: 508 | D9: =L8 | E9: 1045 | F9: 0 | G9: 960 | H9: 80 | I9: 62 | J9: 12 | K9: 0 | L9: =D9+E9+F9-G9-H9-I9-K9 | M9: 104 | N9: 95 | O9: 1045 | P9: 980 | Q9: 473600 | R9: 148000 | S9: 2000 | T9: 2000 | U9: 40 | V9: 37 | W9: 22 | X9: 22 | Y9: 80 | Z9: 80 | AA9: 1045 | AB9: 1045 | AC9: 30 | AD9: 29 | AE9: 9 | AF9: 0 | AG9: 1562880 | AH9: 92000 | AI9: 500000 | AJ9: 116160 | AK9: 20.5 | AL9: =IF(L9=D9+E9+F9-G9-H9-I9-K9,"平衡","不平衡") | AM9: =IF(Z9=Y9,"一致","不一致")
A10: 5月 | B10: =C9 | C10: 510 | D10: =L9 | E10: 1023 | F10: 0 | G10: 940 | H10: 78 | I10: 60 | J10: 13 | K10: 0 | L10: =D10+E10+F10-G10-H10-I10-K10 | M10: 102 | N10: 93 | O10: 1023 | P10: 960 | Q10: 467200 | R10: 146000 | S10: 1950 | T10: 1950 | U10: 38 | V10: 36 | W10: 21 | X10: 21 | Y10: 78 | Z10: 78 | AA10: 1023 | AB10: 1023 | AC10: 31 | AD10: 30 | AE10: 10 | AF10: 0 | AG10: 1541760 | AH10: 88000 | AI10: 500000 | AJ10: 112800 | AK10: 20.3 | AL10: =IF(L10=D10+E10+F10-G10-H10-I10-K10,"平衡","不平衡") | AM10: =IF(Z10=Y10,"一致","不一致")
A11: 6月 | B11: =C10 | C11: 512 | D11: =L10 | E11: 1067 | F11: 0 | G11: 980 | H11: 82 | I11: 58 | J11: 11 | K11: 0 | L11: =D11+E11+F11-G11-H11-I11-K11 | M11: 106 | N11: 97 | O11: 1067 | P11: 1000 | Q11: 486400 | R11: 152000 | S11: 2050 | T11: 2050 | U11: 42 | V11: 39 | W11: 24 | X11: 24 | Y11: 82 | Z11: 82 | AA11: 1067 | AB11: 1067 | AC11: 30 | AD11: 29 | AE11: 9 | AF11: 0 | AG11: 1605120 | AH11: 96000 | AI11: 500000 | AJ11: 119560 | AK11: 19.9 | AL11: =IF(L11=D11+E11+F11-G11-H11-I11-K11,"平衡","不平衡") | AM11: =IF(Z11=Y11,"一致","不一致")
A12: 7月 | B12: =C11 | C12: 510 | D12: =L11 | E12: 1034 | F12: 0 | G12: 950 | H12: 78 | I12: 65 | J12: 15 | K12: 0 | L12: =D12+E12+F12-G12-H12-I12-K12 | M12: 103 | N12: 94 | O12: 1034 | P12: 970 | Q12: 476800 | R12: 149000 | S12: 2000 | T12: 2000 | U12: 40 | V12: 37 | W12: 23 | X12: 23 | Y12: 78 | Z12: 78 | AA12: 1034 | AB12: 1034 | AC12: 31 | AD12: 30 | AE12: 10 | AF12: 0 | AG12: 1573440 | AH12: 93000 | AI12: 500000 | AJ12: 114950 | AK12: 19.6 | AL12: =IF(L12=D12+E12+F12-G12-H12-I12-K12,"平衡","不平衡") | AM12: =IF(Z12=Y12,"一致","不一致")
A13: 8月 | B13: =C12 | C13: 508 | D13: =L12 | E13: 1012 | F13: 0 | G13: 930 | H13: 120 | I13: 60 | J13: 12 | K13: 0 | L13: =D13+E13+F13-G13-H13-I13-K13 | M13: 101 | N13: 92 | O13: 1012 | P13: 950 | Q13: 470400 | R13: 147000 | S13: 1950 | T13: 1950 | U13: 36 | V13: 34 | W13: 22 | X13: 22 | Y13: 120 | Z13: 120 | AA13: 1012 | AB13: 1012 | AC13: 31 | AD13: 30 | AE13: 10 | AF13: 0 | AG13: 1552320 | AH13: 100000 | AI13: 500000 | AJ13: 111600 | AK13: 19.4 | AL13: =IF(L13=D13+E13+F13-G13-H13-I13-K13,"平衡","不平衡") | AM13: =IF(Z13=Y13,"一致","不一致")
A14: 9月 | B14: =C13 | C14: 506 | D14: =L13 | E14: 1078 | F14: 0 | G14: 970 | H14: 78 | I14: 55 | J14: 10 | K14: 0 | L14: =D14+E14+F14-G14-H14-I14-K14 | M14: 107 | N14: 98 | O14: 1078 | P14: 1010 | Q14: 489600 | R14: 153000 | S14: 2100 | T14: 2100 | U14: 44 | V14: 41 | W14: 23 | X14: 23 | Y14: 78 | Z14: 78 | AA14: 1078 | AB14: 1078 | AC14: 30 | AD14: 29 | AE14: 9 | AF14: 0 | AG14: 1615680 | AH14: 91000 | AI14: 500000 | AJ14: 115430 | AK14: 19.7 | AL14: =IF(L14=D14+E14+F14-G14-H14-I14-K14,"平衡","不平衡") | AM14: =IF(Z14=Y14,"一致","不一致")
A15: 10月 | B15: =C14 | C15: 508 | D15: =L14 | E15: 1056 | F15: 0 | G15: 960 | H15: 72 | I15: 58 | J15: 13 | K15: 0 | L15: =D15+E15+F15-G15-H15-I15-K15 | M15: 105 | N15: 96 | O15: 1056 | P15: 990 | Q15: 483200 | R15: 151000 | S15: 2050 | T15: 2050 | U15: 40 | V15: 37 | W15: 24 | X15: 24 | Y15: 72 | Z15: 72 | AA15: 1056 | AB15: 1056 | AC15: 31 | AD15: 29 | AE15: 10 | AF15: 0 | AG15: 1594560 | AH15: 94000 | AI15: 500000 | AJ15: 115200 | AK15: 20.1 | AL15: =IF(L15=D15+E15+F15-G15-H15-I15-K15,"平衡","不平衡") | AM15: =IF(Z15=Y15,"一致","不一致")
A16: 11月 | B16: =C15 | C16: 510 | D16: =L15 | E16: 1034 | F16: 0 | G16: 940 | H16: 70 | I16: 62 | J16: 12 | K16: 0 | L16: =D16+E16+F16-G16-H16-I16-K16 | M16: 103 | N16: 94 | O16: 1034 | P16: 970 | Q16: 473600 | R16: 148000 | S16: 2000 | T16: 2000 | U16: 38 | V16: 36 | W16: 22 | X16: 22 | Y16: 70 | Z16: 70 | AA16: 1034 | AB16: 1034 | AC16: 30 | AD16: 28 | AE16: 9 | AF16: 0 | AG16: 1562880 | AH16: 92000 | AI16: 500000 | AJ16: 113740 | AK16: 20.4 | AL16: =IF(L16=D16+E16+F16-G16-H16-I16-K16,"平衡","不平衡") | AM16: =IF(Z16=Y16,"一致","不一致")
A17: 12月 | B17: =C16 | C17: 512 | D17: =L16 | E17: 1089 | F17: 0 | G17: 1000 | H17: 76 | I17: 60 | J17: 14 | K17: 0 | L17: =D17+E17+F17-G17-H17-I17-K17 | M17: 108 | N17: 99 | O17: 1089 | P17: 1020 | Q17: 492800 | R17: 154000 | S17: 2100 | T17: 2100 | U17: 45 | V17: 42 | W17: 25 | X17: 25 | Y17: 76 | Z17: 76 | AA17: 1089 | AB17: 1089 | AC17: 31 | AD17: 27 | AE17: 10 | AF17: 1 | AG17: 1626240 | AH17: 97000 | AI17: 500000 | AJ17: 122000 | AK17: 20.8 | AL17: =IF(L17=D17+E17+F17-G17-H17-I17-K17,"平衡","不平衡") | AM17: =IF(Z17=Y17,"一致","不一致")

Sheet ④演算-指标计算
A1: ④ 月度指标计算（公式引用③录入区，随档案数据自动刷新）
A2: 全部指标由公式实时计算；红底为触发行业阈值的预警（死亡率>1.5%、抗体合格率<90%等），即看板的自动预警规则。配种分娩率按同月口径演示，生产中应按批次匹配。
A3: 月份 | B3: 月均能繁母猪 | C3: 月均全群存栏 | D3: 月死亡率 | E3: 配种分娩率 | F3: 胎均活仔 | G3: 断奶成活率 | H3: 料肉比 | I3: 出栏均重(kg) | J3: 免疫密度 | K3: 抗体合格率 | L3: 休药期合规率 | M3: 无害化处理率 | N3: 标识佩戴率 | O3: 温度达标率 | P3: 氨气达标率 | Q3: 头均成本(元) | R3: 头均收入(元) | S3: 头均盈利(元)
A6: ='③演算-数据录入'!A6 | B6: =('③演算-数据录入'!B6+'③演算-数据录入'!C6)/2 | C6: =('③演算-数据录入'!D6+'③演算-数据录入'!L6)/2 | D6: =IF(C6=0,"",'③演算-数据录入'!H6/C6) | E6: =IF('③演算-数据录入'!M6=0,"",'③演算-数据录入'!N6/'③演算-数据录入'!M6) | F6: =IF('③演算-数据录入'!N6=0,"",'③演算-数据录入'!O6/'③演算-数据录入'!N6) | G6: =IF('③演算-数据录入'!O6=0,"",'③演算-数据录入'!P6/'③演算-数据录入'!O6) | H6: =IF('③演算-数据录入'!R6=0,"",'③演算-数据录入'!Q6/'③演算-数据录入'!R6) | I6: =IF('③演算-数据录入'!G6=0,"",'③演算-数据录入'!AJ6/'③演算-数据录入'!G6) | J6: =IF('③演算-数据录入'!S6=0,"",'③演算-数据录入'!T6/'③演算-数据录入'!S6) | K6: =IF('③演算-数据录入'!U6=0,"",'③演算-数据录入'!V6/'③演算-数据录入'!U6) | L6: =IF('③演算-数据录入'!W6=0,"",'③演算-数据录入'!X6/'③演算-数据录入'!W6) | M6: =IF('③演算-数据录入'!Y6=0,"",'③演算-数据录入'!Z6/'③演算-数据录入'!Y6) | N6: =IF('③演算-数据录入'!AA6=0,"",'③演算-数据录入'!AB6/'③演算-数据录入'!AA6) | O6: =IF('③演算-数据录入'!AC6=0,"",'③演算-数据录入'!AD6/'③演算-数据录入'!AC6) | P6: =IF('③演算-数据录入'!AE6=0,"",1-'③演算-数据录入'!AF6/'③演算-数据录入'!AE6) | Q6: =IF('③演算-数据录入'!G6=0,"",('③演算-数据录入'!AG6+'③演算-数据录入'!AH6+'③演算-数据录入'!AI6)/'③演算-数据录入'!G6) | R6: =IF('③演算-数据录入'!G6=0,"",'③演算-数据录入'!AK6*'③演算-数据录入'!AJ6/'③演算-数据录入'!G6) | S6: =R6-Q6
A7: ='③演算-数据录入'!A7 | B7: =('③演算-数据录入'!B7+'③演算-数据录入'!C7)/2 | C7: =('③演算-数据录入'!D7+'③演算-数据录入'!L7)/2 | D7: =IF(C7=0,"",'③演算-数据录入'!H7/C7) | E7: =IF('③演算-数据录入'!M7=0,"",'③演算-数据录入'!N7/'③演算-数据录入'!M7) | F7: =IF('③演算-数据录入'!N7=0,"",'③演算-数据录入'!O7/'③演算-数据录入'!N7) | G7: =IF('③演算-数据录入'!O7=0,"",'③演算-数据录入'!P7/'③演算-数据录入'!O7) | H7: =IF('③演算-数据录入'!R7=0,"",'③演算-数据录入'!Q7/'③演算-数据录入'!R7) | I7: =IF('③演算-数据录入'!G7=0,"",'③演算-数据录入'!AJ7/'③演算-数据录入'!G7) | J7: =IF('③演算-数据录入'!S7=0,"",'③演算-数据录入'!T7/'③演算-数据录入'!S7) | K7: =IF('③演算-数据录入'!U7=0,"",'③演算-数据录入'!V7/'③演算-数据录入'!U7) | L7: =IF('③演算-数据录入'!W7=0,"",'③演算-数据录入'!X7/'③演算-数据录入'!W7) | M7: =IF('③演算-数据录入'!Y7=0,"",'③演算-数据录入'!Z7/'③演算-数据录入'!Y7) | N7: =IF('③演算-数据录入'!AA7=0,"",'③演算-数据录入'!AB7/'③演算-数据录入'!AA7) | O7: =IF('③演算-数据录入'!AC7=0,"",'③演算-数据录入'!AD7/'③演算-数据录入'!AC7) | P7: =IF('③演算-数据录入'!AE7=0,"",1-'③演算-数据录入'!AF7/'③演算-数据录入'!AE7) | Q7: =IF('③演算-数据录入'!G7=0,"",('③演算-数据录入'!AG7+'③演算-数据录入'!AH7+'③演算-数据录入'!AI7)/'③演算-数据录入'!G7) | R7: =IF('③演算-数据录入'!G7=0,"",'③演算-数据录入'!AK7*'③演算-数据录入'!AJ7/'③演算-数据录入'!G7) | S7: =R7-Q7
A8: ='③演算-数据录入'!A8 | B8: =('③演算-数据录入'!B8+'③演算-数据录入'!C8)/2 | C8: =('③演算-数据录入'!D8+'③演算-数据录入'!L8)/2 | D8: =IF(C8=0,"",'③演算-数据录入'!H8/C8) | E8: =IF('③演算-数据录入'!M8=0,"",'③演算-数据录入'!N8/'③演算-数据录入'!M8) | F8: =IF('③演算-数据录入'!N8=0,"",'③演算-数据录入'!O8/'③演算-数据录入'!N8) | G8: =IF('③演算-数据录入'!O8=0,"",'③演算-数据录入'!P8/'③演算-数据录入'!O8) | H8: =IF('③演算-数据录入'!R8=0,"",'③演算-数据录入'!Q8/'③演算-数据录入'!R8) | I8: =IF('③演算-数据录入'!G8=0,"",'③演算-数据录入'!AJ8/'③演算-数据录入'!G8) | J8: =IF('③演算-数据录入'!S8=0,"",'③演算-数据录入'!T8/'③演算-数据录入'!S8) | K8: =IF('③演算-数据录入'!U8=0,"",'③演算-数据录入'!V8/'③演算-数据录入'!U8) | L8: =IF('③演算-数据录入'!W8=0,"",'③演算-数据录入'!X8/'③演算-数据录入'!W8) | M8: =IF('③演算-数据录入'!Y8=0,"",'③演算-数据录入'!Z8/'③演算-数据录入'!Y8) | N8: =IF('③演算-数据录入'!AA8=0,"",'③演算-数据录入'!AB8/'③演算-数据录入'!AA8) | O8: =IF('③演算-数据录入'!AC8=0,"",'③演算-数据录入'!AD8/'③演算-数据录入'!AC8) | P8: =IF('③演算-数据录入'!AE8=0,"",1-'③演算-数据录入'!AF8/'③演算-数据录入'!AE8) | Q8: =IF('③演算-数据录入'!G8=0,"",('③演算-数据录入'!AG8+'③演算-数据录入'!AH8+'③演算-数据录入'!AI8)/'③演算-数据录入'!G8) | R8: =IF('③演算-数据录入'!G8=0,"",'③演算-数据录入'!AK8*'③演算-数据录入'!AJ8/'③演算-数据录入'!G8) | S8: =R8-Q8
A9: ='③演算-数据录入'!A9 | B9: =('③演算-数据录入'!B9+'③演算-数据录入'!C9)/2 | C9: =('③演算-数据录入'!D9+'③演算-数据录入'!L9)/2 | D9: =IF(C9=0,"",'③演算-数据录入'!H9/C9) | E9: =IF('③演算-数据录入'!M9=0,"",'③演算-数据录入'!N9/'③演算-数据录入'!M9) | F9: =IF('③演算-数据录入'!N9=0,"",'③演算-数据录入'!O9/'③演算-数据录入'!N9) | G9: =IF('③演算-数据录入'!O9=0,"",'③演算-数据录入'!P9/'③演算-数据录入'!O9) | H9: =IF('③演算-数据录入'!R9=0,"",'③演算-数据录入'!Q9/'③演算-数据录入'!R9) | I9: =IF('③演算-数据录入'!G9=0,"",'③演算-数据录入'!AJ9/'③演算-数据录入'!G9) | J9: =IF('③演算-数据录入'!S9=0,"",'③演算-数据录入'!T9/'③演算-数据录入'!S9) | K9: =IF('③演算-数据录入'!U9=0,"",'③演算-数据录入'!V9/'③演算-数据录入'!U9) | L9: =IF('③演算-数据录入'!W9=0,"",'③演算-数据录入'!X9/'③演算-数据录入'!W9) | M9: =IF('③演算-数据录入'!Y9=0,"",'③演算-数据录入'!Z9/'③演算-数据录入'!Y9) | N9: =IF('③演算-数据录入'!AA9=0,"",'③演算-数据录入'!AB9/'③演算-数据录入'!AA9) | O9: =IF('③演算-数据录入'!AC9=0,"",'③演算-数据录入'!AD9/'③演算-数据录入'!AC9) | P9: =IF('③演算-数据录入'!AE9=0,"",1-'③演算-数据录入'!AF9/'③演算-数据录入'!AE9) | Q9: =IF('③演算-数据录入'!G9=0,"",('③演算-数据录入'!AG9+'③演算-数据录入'!AH9+'③演算-数据录入'!AI9)/'③演算-数据录入'!G9) | R9: =IF('③演算-数据录入'!G9=0,"",'③演算-数据录入'!AK9*'③演算-数据录入'!AJ9/'③演算-数据录入'!G9) | S9: =R9-Q9
A10: ='③演算-数据录入'!A10 | B10: =('③演算-数据录入'!B10+'③演算-数据录入'!C10)/2 | C10: =('③演算-数据录入'!D10+'③演算-数据录入'!L10)/2 | D10: =IF(C10=0,"",'③演算-数据录入'!H10/C10) | E10: =IF('③演算-数据录入'!M10=0,"",'③演算-数据录入'!N10/'③演算-数据录入'!M10) | F10: =IF('③演算-数据录入'!N10=0,"",'③演算-数据录入'!O10/'③演算-数据录入'!N10) | G10: =IF('③演算-数据录入'!O10=0,"",'③演算-数据录入'!P10/'③演算-数据录入'!O10) | H10: =IF('③演算-数据录入'!R10=0,"",'③演算-数据录入'!Q10/'③演算-数据录入'!R10) | I10: =IF('③演算-数据录入'!G10=0,"",'③演算-数据录入'!AJ10/'③演算-数据录入'!G10) | J10: =IF('③演算-数据录入'!S10=0,"",'③演算-数据录入'!T10/'③演算-数据录入'!S10) | K10: =IF('③演算-数据录入'!U10=0,"",'③演算-数据录入'!V10/'③演算-数据录入'!U10) | L10: =IF('③演算-数据录入'!W10=0,"",'③演算-数据录入'!X10/'③演算-数据录入'!W10) | M10: =IF('③演算-数据录入'!Y10=0,"",'③演算-数据录入'!Z10/'③演算-数据录入'!Y10) | N10: =IF('③演算-数据录入'!AA10=0,"",'③演算-数据录入'!AB10/'③演算-数据录入'!AA10) | O10: =IF('③演算-数据录入'!AC10=0,"",'③演算-数据录入'!AD10/'③演算-数据录入'!AC10) | P10: =IF('③演算-数据录入'!AE10=0,"",1-'③演算-数据录入'!AF10/'③演算-数据录入'!AE10) | Q10: =IF('③演算-数据录入'!G10=0,"",('③演算-数据录入'!AG10+'③演算-数据录入'!AH10+'③演算-数据录入'!AI10)/'③演算-数据录入'!G10) | R10: =IF('③演算-数据录入'!G10=0,"",'③演算-数据录入'!AK10*'③演算-数据录入'!AJ10/'③演算-数据录入'!G10) | S10: =R10-Q10
A11: ='③演算-数据录入'!A11 | B11: =('③演算-数据录入'!B11+'③演算-数据录入'!C11)/2 | C11: =('③演算-数据录入'!D11+'③演算-数据录入'!L11)/2 | D11: =IF(C11=0,"",'③演算-数据录入'!H11/C11) | E11: =IF('③演算-数据录入'!M11=0,"",'③演算-数据录入'!N11/'③演算-数据录入'!M11) | F11: =IF('③演算-数据录入'!N11=0,"",'③演算-数据录入'!O11/'③演算-数据录入'!N11) | G11: =IF('③演算-数据录入'!O11=0,"",'③演算-数据录入'!P11/'③演算-数据录入'!O11) | H11: =IF('③演算-数据录入'!R11=0,"",'③演算-数据录入'!Q11/'③演算-数据录入'!R11) | I11: =IF('③演算-数据录入'!G11=0,"",'③演算-数据录入'!AJ11/'③演算-数据录入'!G11) | J11: =IF('③演算-数据录入'!S11=0,"",'③演算-数据录入'!T11/'③演算-数据录入'!S11) | K11: =IF('③演算-数据录入'!U11=0,"",'③演算-数据录入'!V11/'③演算-数据录入'!U11) | L11: =IF('③演算-数据录入'!W11=0,"",'③演算-数据录入'!X11/'③演算-数据录入'!W11) | M11: =IF('③演算-数据录入'!Y11=0,"",'③演算-数据录入'!Z11/'③演算-数据录入'!Y11) | N11: =IF('③演算-数据录入'!AA11=0,"",'③演算-数据录入'!AB11/'③演算-数据录入'!AA11) | O11: =IF('③演算-数据录入'!AC11=0,"",'③演算-数据录入'!AD11/'③演算-数据录入'!AC11) | P11: =IF('③演算-数据录入'!AE11=0,"",1-'③演算-数据录入'!AF11/'③演算-数据录入'!AE11) | Q11: =IF('③演算-数据录入'!G11=0,"",('③演算-数据录入'!AG11+'③演算-数据录入'!AH11+'③演算-数据录入'!AI11)/'③演算-数据录入'!G11) | R11: =IF('③演算-数据录入'!G11=0,"",'③演算-数据录入'!AK11*'③演算-数据录入'!AJ11/'③演算-数据录入'!G11) | S11: =R11-Q11
A12: ='③演算-数据录入'!A12 | B12: =('③演算-数据录入'!B12+'③演算-数据录入'!C12)/2 | C12: =('③演算-数据录入'!D12+'③演算-数据录入'!L12)/2 | D12: =IF(C12=0,"",'③演算-数据录入'!H12/C12) | E12: =IF('③演算-数据录入'!M12=0,"",'③演算-数据录入'!N12/'③演算-数据录入'!M12) | F12: =IF('③演算-数据录入'!N12=0,"",'③演算-数据录入'!O12/'③演算-数据录入'!N12) | G12: =IF('③演算-数据录入'!O12=0,"",'③演算-数据录入'!P12/'③演算-数据录入'!O12) | H12: =IF('③演算-数据录入'!R12=0,"",'③演算-数据录入'!Q12/'③演算-数据录入'!R12) | I12: =IF('③演算-数据录入'!G12=0,"",'③演算-数据录入'!AJ12/'③演算-数据录入'!G12) | J12: =IF('③演算-数据录入'!S12=0,"",'③演算-数据录入'!T12/'③演算-数据录入'!S12) | K12: =IF('③演算-数据录入'!U12=0,"",'③演算-数据录入'!V12/'③演算-数据录入'!U12) | L12: =IF('③演算-数据录入'!W12=0,"",'③演算-数据录入'!X12/'③演算-数据录入'!W12) | M12: =IF('③演算-数据录入'!Y12=0,"",'③演算-数据录入'!Z12/'③演算-数据录入'!Y12) | N12: =IF('③演算-数据录入'!AA12=0,"",'③演算-数据录入'!AB12/'③演算-数据录入'!AA12) | O12: =IF('③演算-数据录入'!AC12=0,"",'③演算-数据录入'!AD12/'③演算-数据录入'!AC12) | P12: =IF('③演算-数据录入'!AE12=0,"",1-'③演算-数据录入'!AF12/'③演算-数据录入'!AE12) | Q12: =IF('③演算-数据录入'!G12=0,"",('③演算-数据录入'!AG12+'③演算-数据录入'!AH12+'③演算-数据录入'!AI12)/'③演算-数据录入'!G12) | R12: =IF('③演算-数据录入'!G12=0,"",'③演算-数据录入'!AK12*'③演算-数据录入'!AJ12/'③演算-数据录入'!G12) | S12: =R12-Q12
A13: ='③演算-数据录入'!A13 | B13: =('③演算-数据录入'!B13+'③演算-数据录入'!C13)/2 | C13: =('③演算-数据录入'!D13+'③演算-数据录入'!L13)/2 | D13: =IF(C13=0,"",'③演算-数据录入'!H13/C13) | E13: =IF('③演算-数据录入'!M13=0,"",'③演算-数据录入'!N13/'③演算-数据录入'!M13) | F13: =IF('③演算-数据录入'!N13=0,"",'③演算-数据录入'!O13/'③演算-数据录入'!N13) | G13: =IF('③演算-数据录入'!O13=0,"",'③演算-数据录入'!P13/'③演算-数据录入'!O13) | H13: =IF('③演算-数据录入'!R13=0,"",'③演算-数据录入'!Q13/'③演算-数据录入'!R13) | I13: =IF('③演算-数据录入'!G13=0,"",'③演算-数据录入'!AJ13/'③演算-数据录入'!G13) | J13: =IF('③演算-数据录入'!S13=0,"",'③演算-数据录入'!T13/'③演算-数据录入'!S13) | K13: =IF('③演算-数据录入'!U13=0,"",'③演算-数据录入'!V13/'③演算-数据录入'!U13) | L13: =IF('③演算-数据录入'!W13=0,"",'③演算-数据录入'!X13/'③演算-数据录入'!W13) | M13: =IF('③演算-数据录入'!Y13=0,"",'③演算-数据录入'!Z13/'③演算-数据录入'!Y13) | N13: =IF('③演算-数据录入'!AA13=0,"",'③演算-数据录入'!AB13/'③演算-数据录入'!AA13) | O13: =IF('③演算-数据录入'!AC13=0,"",'③演算-数据录入'!AD13/'③演算-数据录入'!AC13) | P13: =IF('③演算-数据录入'!AE13=0,"",1-'③演算-数据录入'!AF13/'③演算-数据录入'!AE13) | Q13: =IF('③演算-数据录入'!G13=0,"",('③演算-数据录入'!AG13+'③演算-数据录入'!AH13+'③演算-数据录入'!AI13)/'③演算-数据录入'!G13) | R13: =IF('③演算-数据录入'!G13=0,"",'③演算-数据录入'!AK13*'③演算-数据录入'!AJ13/'③演算-数据录入'!G13) | S13: =R13-Q13
A14: ='③演算-数据录入'!A14 | B14: =('③演算-数据录入'!B14+'③演算-数据录入'!C14)/2 | C14: =('③演算-数据录入'!D14+'③演算-数据录入'!L14)/2 | D14: =IF(C14=0,"",'③演算-数据录入'!H14/C14) | E14: =IF('③演算-数据录入'!M14=0,"",'③演算-数据录入'!N14/'③演算-数据录入'!M14) | F14: =IF('③演算-数据录入'!N14=0,"",'③演算-数据录入'!O14/'③演算-数据录入'!N14) | G14: =IF('③演算-数据录入'!O14=0,"",'③演算-数据录入'!P14/'③演算-数据录入'!O14) | H14: =IF('③演算-数据录入'!R14=0,"",'③演算-数据录入'!Q14/'③演算-数据录入'!R14) | I14: =IF('③演算-数据录入'!G14=0,"",'③演算-数据录入'!AJ14/'③演算-数据录入'!G14) | J14: =IF('③演算-数据录入'!S14=0,"",'③演算-数据录入'!T14/'③演算-数据录入'!S14) | K14: =IF('③演算-数据录入'!U14=0,"",'③演算-数据录入'!V14/'③演算-数据录入'!U14) | L14: =IF('③演算-数据录入'!W14=0,"",'③演算-数据录入'!X14/'③演算-数据录入'!W14) | M14: =IF('③演算-数据录入'!Y14=0,"",'③演算-数据录入'!Z14/'③演算-数据录入'!Y14) | N14: =IF('③演算-数据录入'!AA14=0,"",'③演算-数据录入'!AB14/'③演算-数据录入'!AA14) | O14: =IF('③演算-数据录入'!AC14=0,"",'③演算-数据录入'!AD14/'③演算-数据录入'!AC14) | P14: =IF('③演算-数据录入'!AE14=0,"",1-'③演算-数据录入'!AF14/'③演算-数据录入'!AE14) | Q14: =IF('③演算-数据录入'!G14=0,"",('③演算-数据录入'!AG14+'③演算-数据录入'!AH14+'③演算-数据录入'!AI14)/'③演算-数据录入'!G14) | R14: =IF('③演算-数据录入'!G14=0,"",'③演算-数据录入'!AK14*'③演算-数据录入'!AJ14/'③演算-数据录入'!G14) | S14: =R14-Q14
A15: ='③演算-数据录入'!A15 | B15: =('③演算-数据录入'!B15+'③演算-数据录入'!C15)/2 | C15: =('③演算-数据录入'!D15+'③演算-数据录入'!L15)/2 | D15: =IF(C15=0,"",'③演算-数据录入'!H15/C15) | E15: =IF('③演算-数据录入'!M15=0,"",'③演算-数据录入'!N15/'③演算-数据录入'!M15) | F15: =IF('③演算-数据录入'!N15=0,"",'③演算-数据录入'!O15/'③演算-数据录入'!N15) | G15: =IF('③演算-数据录入'!O15=0,"",'③演算-数据录入'!P15/'③演算-数据录入'!O15) | H15: =IF('③演算-数据录入'!R15=0,"",'③演算-数据录入'!Q15/'③演算-数据录入'!R15) | I15: =IF('③演算-数据录入'!G15=0,"",'③演算-数据录入'!AJ15/'③演算-数据录入'!G15) | J15: =IF('③演算-数据录入'!S15=0,"",'③演算-数据录入'!T15/'③演算-数据录入'!S15) | K15: =IF('③演算-数据录入'!U15=0,"",'③演算-数据录入'!V15/'③演算-数据录入'!U15) | L15: =IF('③演算-数据录入'!W15=0,"",'③演算-数据录入'!X15/'③演算-数据录入'!W15) | M15: =IF('③演算-数据录入'!Y15=0,"",'③演算-数据录入'!Z15/'③演算-数据录入'!Y15) | N15: =IF('③演算-数据录入'!AA15=0,"",'③演算-数据录入'!AB15/'③演算-数据录入'!AA15) | O15: =IF('③演算-数据录入'!AC15=0,"",'③演算-数据录入'!AD15/'③演算-数据录入'!AC15) | P15: =IF('③演算-数据录入'!AE15=0,"",1-'③演算-数据录入'!AF15/'③演算-数据录入'!AE15) | Q15: =IF('③演算-数据录入'!G15=0,"",('③演算-数据录入'!AG15+'③演算-数据录入'!AH15+'③演算-数据录入'!AI15)/'③演算-数据录入'!G15) | R15: =IF('③演算-数据录入'!G15=0,"",'③演算-数据录入'!AK15*'③演算-数据录入'!AJ15/'③演算-数据录入'!G15) | S15: =R15-Q15
A16: ='③演算-数据录入'!A16 | B16: =('③演算-数据录入'!B16+'③演算-数据录入'!C16)/2 | C16: =('③演算-数据录入'!D16+'③演算-数据录入'!L16)/2 | D16: =IF(C16=0,"",'③演算-数据录入'!H16/C16) | E16: =IF('③演算-数据录入'!M16=0,"",'③演算-数据录入'!N16/'③演算-数据录入'!M16) | F16: =IF('③演算-数据录入'!N16=0,"",'③演算-数据录入'!O16/'③演算-数据录入'!N16) | G16: =IF('③演算-数据录入'!O16=0,"",'③演算-数据录入'!P16/'③演算-数据录入'!O16) | H16: =IF('③演算-数据录入'!R16=0,"",'③演算-数据录入'!Q16/'③演算-数据录入'!R16) | I16: =IF('③演算-数据录入'!G16=0,"",'③演算-数据录入'!AJ16/'③演算-数据录入'!G16) | J16: =IF('③演算-数据录入'!S16=0,"",'③演算-数据录入'!T16/'③演算-数据录入'!S16) | K16: =IF('③演算-数据录入'!U16=0,"",'③演算-数据录入'!V16/'③演算-数据录入'!U16) | L16: =IF('③演算-数据录入'!W16=0,"",'③演算-数据录入'!X16/'③演算-数据录入'!W16) | M16: =IF('③演算-数据录入'!Y16=0,"",'③演算-数据录入'!Z16/'③演算-数据录入'!Y16) | N16: =IF('③演算-数据录入'!AA16=0,"",'③演算-数据录入'!AB16/'③演算-数据录入'!AA16) | O16: =IF('③演算-数据录入'!AC16=0,"",'③演算-数据录入'!AD16/'③演算-数据录入'!AC16) | P16: =IF('③演算-数据录入'!AE16=0,"",1-'③演算-数据录入'!AF16/'③演算-数据录入'!AE16) | Q16: =IF('③演算-数据录入'!G16=0,"",('③演算-数据录入'!AG16+'③演算-数据录入'!AH16+'③演算-数据录入'!AI16)/'③演算-数据录入'!G16) | R16: =IF('③演算-数据录入'!G16=0,"",'③演算-数据录入'!AK16*'③演算-数据录入'!AJ16/'③演算-数据录入'!G16) | S16: =R16-Q16
A17: ='③演算-数据录入'!A17 | B17: =('③演算-数据录入'!B17+'③演算-数据录入'!C17)/2 | C17: =('③演算-数据录入'!D17+'③演算-数据录入'!L17)/2 | D17: =IF(C17=0,"",'③演算-数据录入'!H17/C17) | E17: =IF('③演算-数据录入'!M17=0,"",'③演算-数据录入'!N17/'③演算-数据录入'!M17) | F17: =IF('③演算-数据录入'!N17=0,"",'③演算-数据录入'!O17/'③演算-数据录入'!N17) | G17: =IF('③演算-数据录入'!O17=0,"",'③演算-数据录入'!P17/'③演算-数据录入'!O17) | H17: =IF('③演算-数据录入'!R17=0,"",'③演算-数据录入'!Q17/'③演算-数据录入'!R17) | I17: =IF('③演算-数据录入'!G17=0,"",'③演算-数据录入'!AJ17/'③演算-数据录入'!G17) | J17: =IF('③演算-数据录入'!S17=0,"",'③演算-数据录入'!T17/'③演算-数据录入'!S17) | K17: =IF('③演算-数据录入'!U17=0,"",'③演算-数据录入'!V17/'③演算-数据录入'!U17) | L17: =IF('③演算-数据录入'!W17=0,"",'③演算-数据录入'!X17/'③演算-数据录入'!W17) | M17: =IF('③演算-数据录入'!Y17=0,"",'③演算-数据录入'!Z17/'③演算-数据录入'!Y17) | N17: =IF('③演算-数据录入'!AA17=0,"",'③演算-数据录入'!AB17/'③演算-数据录入'!AA17) | O17: =IF('③演算-数据录入'!AC17=0,"",'③演算-数据录入'!AD17/'③演算-数据录入'!AC17) | P17: =IF('③演算-数据录入'!AE17=0,"",1-'③演算-数据录入'!AF17/'③演算-数据录入'!AE17) | Q17: =IF('③演算-数据录入'!G17=0,"",('③演算-数据录入'!AG17+'③演算-数据录入'!AH17+'③演算-数据录入'!AI17)/'③演算-数据录入'!G17) | R17: =IF('③演算-数据录入'!G17=0,"",'③演算-数据录入'!AK17*'③演算-数据录入'!AJ17/'③演算-数据录入'!G17) | S17: =R17-Q17
A20: 年度综合KPI与阈值断言
A21: 年度指标 | B21: 单位 | C21: 数值 | D21: 参考下限 | E21: 参考上限 | F21: 优秀/目标 | G21: 判定规则 | H21: 判定结果
A22: PSY | B22: 头 | C22: =SUM('③演算-数据录入'!P6:P17)/AVERAGE(B6:B17) | D22: 22 | E22: 28 | F22: 30 | G22: 低于下限=异常；达到目标=优秀 | H22: =IF(ISNUMBER(D22),IF(C22<D22,"异常",IF(AND(ISNUMBER(F22),C22>=F22),"优秀","达标")),"")
A23: MSY | B23: 头 | C23: =SUM('③演算-数据录入'!G6:G17)/AVERAGE(B6:B17) | D23: 20 | E23: 25 | F23: 27 | G23: 低于下限=异常；达到目标=优秀 | H23: =IF(ISNUMBER(D23),IF(C23<D23,"异常",IF(AND(ISNUMBER(F23),C23>=F23),"优秀","达标")),"")
A24: 母猪年产胎次 | B24: 胎 | C24: =SUM('③演算-数据录入'!N6:N17)/AVERAGE(B6:B17) | D24: 2.2 | E24: 2.4 | F24: 2.45 | G24: 低于下限=异常；达到目标=优秀 | H24: =IF(ISNUMBER(D24),IF(C24<D24,"异常",IF(AND(ISNUMBER(F24),C24>=F24),"优秀","达标")),"")
A25: 胎均活仔 | B25: 头 | C25: =SUM('③演算-数据录入'!O6:O17)/SUM('③演算-数据录入'!N6:N17) | D25: 10 | E25: 13 | F25: 13 | G25: 落在区间=达标；达到目标=优秀 | H25: =IF(OR(C25<D25,C25>E25),"异常",IF(AND(ISNUMBER(F25),C25>=F25),"优秀","达标"))
A26: 全程成活率 | B26: % | C26: =SUM('③演算-数据录入'!G6:G17)/SUM('③演算-数据录入'!O6:O17) | D26: 0.85 | E26: 0.92 | F26: 0.93 | G26: 低于下限=异常；达到目标=优秀 | H26: =IF(ISNUMBER(D26),IF(C26<D26,"异常",IF(AND(ISNUMBER(F26),C26>=F26),"优秀","达标")),"")
A27: 月均死亡率 | B27: % | C27: =AVERAGE(D6:D17) | E27: 0.015 | F27: 0.01 | G27: 超过上限=异常；达到目标=优秀 | H27: =IF(ISNUMBER(E27),IF(C27>E27,"异常",IF(AND(ISNUMBER(F27),C27<=F27),"优秀","达标")),"")
A28: 年料肉比 | B28: :1 | C28: =SUM('③演算-数据录入'!Q6:Q17)/SUM('③演算-数据录入'!R6:R17) | D28: 3 | E28: 3.4 | F28: 2.9 | G28: 超过上限=异常；达到目标=优秀 | H28: =IF(ISNUMBER(E28),IF(C28>E28,"异常",IF(AND(ISNUMBER(F28),C28<=F28),"优秀","达标")),"")
A29: 年出栏均重 | B29: kg | C29: =SUM('③演算-数据录入'!AJ6:AJ17)/SUM('③演算-数据录入'!G6:G17) | D29: 110 | E29: 130 | F29: 125 | G29: 落在区间=达标；达到目标=优秀 | H29: =IF(OR(C29<D29,C29>E29),"异常",IF(AND(ISNUMBER(F29),C29>=F29),"优秀","达标"))
A30: 年免疫密度 | B30: % | C30: =SUM('③演算-数据录入'!T6:T17)/SUM('③演算-数据录入'!S6:S17) | F30: 1 | G30: 达到目标=达标，否则异常 | H30: =IF(C30>=F30,"达标","异常")
A31: 年抗体合格率 | B31: % | C31: =SUM('③演算-数据录入'!V6:V17)/SUM('③演算-数据录入'!U6:U17) | D31: 0.9 | F31: 0.95 | G31: 低于下限=异常；达到目标=优秀 | H31: =IF(ISNUMBER(D31),IF(C31<D31,"异常",IF(AND(ISNUMBER(F31),C31>=F31),"优秀","达标")),"")
A32: 年休药期合规率 | B32: % | C32: =SUM('③演算-数据录入'!X6:X17)/SUM('③演算-数据录入'!W6:W17) | F32: 1 | G32: 达到目标=达标，否则异常 | H32: =IF(C32>=F32,"达标","异常")
A33: 年无害化处理率 | B33: % | C33: =SUM('③演算-数据录入'!Z6:Z17)/SUM('③演算-数据录入'!Y6:Y17) | F33: 1 | G33: 达到目标=达标，否则异常 | H33: =IF(C33>=F33,"达标","异常")
A34: 年标识佩戴率 | B34: % | C34: =SUM('③演算-数据录入'!AB6:AB17)/SUM('③演算-数据录入'!AA6:AA17) | F34: 1 | G34: 达到目标=达标，否则异常 | H34: =IF(C34>=F34,"达标","异常")
A35: 年温度达标率 | B35: % | C35: =SUM('③演算-数据录入'!AD6:AD17)/SUM('③演算-数据录入'!AC6:AC17) | D35: 0.9 | F35: 0.95 | G35: 低于下限=异常；达到目标=优秀 | H35: =IF(ISNUMBER(D35),IF(C35<D35,"异常",IF(AND(ISNUMBER(F35),C35>=F35),"优秀","达标")),"")
A36: 年氨气达标率 | B36: % | C36: =1-SUM('③演算-数据录入'!AF6:AF17)/SUM('③演算-数据录入'!AE6:AE17) | F36: 0.95 | G36: 达到目标=达标，否则异常 | H36: =IF(C36>=F36,"达标","异常")
A37: 头均兽药成本 | B37: 元 | C37: =SUM('③演算-数据录入'!AH6:AH17)/SUM('③演算-数据录入'!G6:G17) | D37: 50 | E37: 120 | G37: 落在区间=达标；达到目标=优秀 | H37: =IF(OR(C37<D37,C37>E37),"异常",IF(AND(ISNUMBER(F37),C37>=F37),"优秀","达标"))
A38: 全程头均成本 | B38: 元 | C38: =(SUM('③演算-数据录入'!AG6:AG17)+SUM('③演算-数据录入'!AH6:AH17)+SUM('③演算-数据录入'!AI6:AI17))/SUM('③演算-数据录入'!G6:G17) | G38: 无统一参考，不判定 | H38: =""
A39: 头均盈利 | B39: 元 | C39: =(SUMPRODUCT('③演算-数据录入'!AK6:AK17,'③演算-数据录入'!AJ6:AJ17)-SUM('③演算-数据录入'!AG6:AG17)-SUM('③演算-数据录入'!AH6:AH17)-SUM('③演算-数据录入'!AI6:AI17))/SUM('③演算-数据录入'!G6:G17) | G39: 无统一参考，不判定 | H39: =""

Sheet ⑤可视化数据准备
A1: ⑤ 可视化数据准备（标准月度宽表 · 可直接作为图表数据源）
A2: 本表结构即为看板数据源：一行一个月、一列一个指标，全部为公式引用④计算结果；图表建议——死亡率/料肉比/抗体合格率用折线（带阈值参考线），合规类用仪表盘或进度条，成本盈利用柱线组合图，年度KPI用大数字卡片。
A4: 月份 | B4: 月死亡率 | C4: 料肉比 | D4: 胎均活仔 | E4: 断奶成活率 | F4: 出栏均重(kg) | G4: 免疫密度 | H4: 抗体合格率 | I4: 休药期合规率 | J4: 无害化处理率 | K4: 温度达标率 | L4: 头均成本(元) | M4: 头均盈利(元)
A5: ='④演算-指标计算'!A6 | B5: ='④演算-指标计算'!D6 | C5: ='④演算-指标计算'!H6 | D5: ='④演算-指标计算'!F6 | E5: ='④演算-指标计算'!G6 | F5: ='④演算-指标计算'!I6 | G5: ='④演算-指标计算'!J6 | H5: ='④演算-指标计算'!K6 | I5: ='④演算-指标计算'!L6 | J5: ='④演算-指标计算'!M6 | K5: ='④演算-指标计算'!O6 | L5: ='④演算-指标计算'!Q6 | M5: ='④演算-指标计算'!S6
A6: ='④演算-指标计算'!A7 | B6: ='④演算-指标计算'!D7 | C6: ='④演算-指标计算'!H7 | D6: ='④演算-指标计算'!F7 | E6: ='④演算-指标计算'!G7 | F6: ='④演算-指标计算'!I7 | G6: ='④演算-指标计算'!J7 | H6: ='④演算-指标计算'!K7 | I6: ='④演算-指标计算'!L7 | J6: ='④演算-指标计算'!M7 | K6: ='④演算-指标计算'!O7 | L6: ='④演算-指标计算'!Q7 | M6: ='④演算-指标计算'!S7
A7: ='④演算-指标计算'!A8 | B7: ='④演算-指标计算'!D8 | C7: ='④演算-指标计算'!H8 | D7: ='④演算-指标计算'!F8 | E7: ='④演算-指标计算'!G8 | F7: ='④演算-指标计算'!I8 | G7: ='④演算-指标计算'!J8 | H7: ='④演算-指标计算'!K8 | I7: ='④演算-指标计算'!L8 | J7: ='④演算-指标计算'!M8 | K7: ='④演算-指标计算'!O8 | L7: ='④演算-指标计算'!Q8 | M7: ='④演算-指标计算'!S8
A8: ='④演算-指标计算'!A9 | B8: ='④演算-指标计算'!D9 | C8: ='④演算-指标计算'!H9 | D8: ='④演算-指标计算'!F9 | E8: ='④演算-指标计算'!G9 | F8: ='④演算-指标计算'!I9 | G8: ='④演算-指标计算'!J9 | H8: ='④演算-指标计算'!K9 | I8: ='④演算-指标计算'!L9 | J8: ='④演算-指标计算'!M9 | K8: ='④演算-指标计算'!O9 | L8: ='④演算-指标计算'!Q9 | M8: ='④演算-指标计算'!S9
A9: ='④演算-指标计算'!A10 | B9: ='④演算-指标计算'!D10 | C9: ='④演算-指标计算'!H10 | D9: ='④演算-指标计算'!F10 | E9: ='④演算-指标计算'!G10 | F9: ='④演算-指标计算'!I10 | G9: ='④演算-指标计算'!J10 | H9: ='④演算-指标计算'!K10 | I9: ='④演算-指标计算'!L10 | J9: ='④演算-指标计算'!M10 | K9: ='④演算-指标计算'!O10 | L9: ='④演算-指标计算'!Q10 | M9: ='④演算-指标计算'!S10
A10: ='④演算-指标计算'!A11 | B10: ='④演算-指标计算'!D11 | C10: ='④演算-指标计算'!H11 | D10: ='④演算-指标计算'!F11 | E10: ='④演算-指标计算'!G11 | F10: ='④演算-指标计算'!I11 | G10: ='④演算-指标计算'!J11 | H10: ='④演算-指标计算'!K11 | I10: ='④演算-指标计算'!L11 | J10: ='④演算-指标计算'!M11 | K10: ='④演算-指标计算'!O11 | L10: ='④演算-指标计算'!Q11 | M10: ='④演算-指标计算'!S11
A11: ='④演算-指标计算'!A12 | B11: ='④演算-指标计算'!D12 | C11: ='④演算-指标计算'!H12 | D11: ='④演算-指标计算'!F12 | E11: ='④演算-指标计算'!G12 | F11: ='④演算-指标计算'!I12 | G11: ='④演算-指标计算'!J12 | H11: ='④演算-指标计算'!K12 | I11: ='④演算-指标计算'!L12 | J11: ='④演算-指标计算'!M12 | K11: ='④演算-指标计算'!O12 | L11: ='④演算-指标计算'!Q12 | M11: ='④演算-指标计算'!S12
A12: ='④演算-指标计算'!A13 | B12: ='④演算-指标计算'!D13 | C12: ='④演算-指标计算'!H13 | D12: ='④演算-指标计算'!F13 | E12: ='④演算-指标计算'!G13 | F12: ='④演算-指标计算'!I13 | G12: ='④演算-指标计算'!J13 | H12: ='④演算-指标计算'!K13 | I12: ='④演算-指标计算'!L13 | J12: ='④演算-指标计算'!M13 | K12: ='④演算-指标计算'!O13 | L12: ='④演算-指标计算'!Q13 | M12: ='④演算-指标计算'!S13
A13: ='④演算-指标计算'!A14 | B13: ='④演算-指标计算'!D14 | C13: ='④演算-指标计算'!H14 | D13: ='④演算-指标计算'!F14 | E13: ='④演算-指标计算'!G14 | F13: ='④演算-指标计算'!I14 | G13: ='④演算-指标计算'!J14 | H13: ='④演算-指标计算'!K14 | I13: ='④演算-指标计算'!L14 | J13: ='④演算-指标计算'!M14 | K13: ='④演算-指标计算'!O14 | L13: ='④演算-指标计算'!Q14 | M13: ='④演算-指标计算'!S14
A14: ='④演算-指标计算'!A15 | B14: ='④演算-指标计算'!D15 | C14: ='④演算-指标计算'!H15 | D14: ='④演算-指标计算'!F15 | E14: ='④演算-指标计算'!G15 | F14: ='④演算-指标计算'!I15 | G14: ='④演算-指标计算'!J15 | H14: ='④演算-指标计算'!K15 | I14: ='④演算-指标计算'!L15 | J14: ='④演算-指标计算'!M15 | K14: ='④演算-指标计算'!O15 | L14: ='④演算-指标计算'!Q15 | M14: ='④演算-指标计算'!S15
A15: ='④演算-指标计算'!A16 | B15: ='④演算-指标计算'!D16 | C15: ='④演算-指标计算'!H16 | D15: ='④演算-指标计算'!F16 | E15: ='④演算-指标计算'!G16 | F15: ='④演算-指标计算'!I16 | G15: ='④演算-指标计算'!J16 | H15: ='④演算-指标计算'!K16 | I15: ='④演算-指标计算'!L16 | J15: ='④演算-指标计算'!M16 | K15: ='④演算-指标计算'!O16 | L15: ='④演算-指标计算'!Q16 | M15: ='④演算-指标计算'!S16
A16: ='④演算-指标计算'!A17 | B16: ='④演算-指标计算'!D17 | C16: ='④演算-指标计算'!H17 | D16: ='④演算-指标计算'!F17 | E16: ='④演算-指标计算'!G17 | F16: ='④演算-指标计算'!I17 | G16: ='④演算-指标计算'!J17 | H16: ='④演算-指标计算'!K17 | I16: ='④演算-指标计算'!L17 | J16: ='④演算-指标计算'!M17 | K16: ='④演算-指标计算'!O17 | L16: ='④演算-指标计算'!Q17 | M16: ='④演算-指标计算'!S17
A19: 年度KPI卡片数据源（看板顶部大数字卡片）
A20: KPI | B20: 数值 | C20: 单位 | D20: 目标值 | E20: 状态
A21: PSY | B21: ='④演算-指标计算'!C22 | C21: ='④演算-指标计算'!B22 | D21: ='④演算-指标计算'!F22 | E21: ='④演算-指标计算'!H22
A22: MSY | B22: ='④演算-指标计算'!C23 | C22: ='④演算-指标计算'!B23 | D22: ='④演算-指标计算'!F23 | E22: ='④演算-指标计算'!H23
A23: 全程成活率 | B23: ='④演算-指标计算'!C26 | C23: ='④演算-指标计算'!B26 | D23: ='④演算-指标计算'!F26 | E23: ='④演算-指标计算'!H26
A24: 月均死亡率 | B24: ='④演算-指标计算'!C27 | C24: ='④演算-指标计算'!B27 | D24: ='④演算-指标计算'!F27 | E24: ='④演算-指标计算'!H27
A25: 年料肉比 | B25: ='④演算-指标计算'!C28 | C25: ='④演算-指标计算'!B28 | D25: ='④演算-指标计算'!F28 | E25: ='④演算-指标计算'!H28
A26: 年抗体合格率 | B26: ='④演算-指标计算'!C31 | C26: ='④演算-指标计算'!B31 | D26: ='④演算-指标计算'!F31 | E26: ='④演算-指标计算'!H31
A27: 年休药期合规率 | B27: ='④演算-指标计算'!C32 | C27: ='④演算-指标计算'!B32 | D27: ='④演算-指标计算'!F32 | E27: ='④演算-指标计算'!H32
A28: 年无害化处理率 | B28: ='④演算-指标计算'!C33 | C28: ='④演算-指标计算'!B33 | D28: ='④演算-指标计算'!F33 | E28: ='④演算-指标计算'!H33
A29: 头均盈利 | B29: ='④演算-指标计算'!C39 | C29: ='④演算-指标计算'!B39 | D29: ='④演算-指标计算'!F39 | E29: ='④演算-指标计算'!H39
